{
"meta":{"test_sets":[],"test_metrics":[],"learn_metrics":[{"best_value":"Min","name":"RMSE"}],"launch_mode":"Train","parameters":"","iteration_count":1000,"learn_sets":["learn"],"name":"experiment"},
"iterations":[
{"learn":[14.54513411],"iteration":0,"passed_time":0.1532694713,"remaining_time":153.1162018},
{"learn":[14.20343568],"iteration":1,"passed_time":0.1541970893,"remaining_time":76.94434754},
{"learn":[13.84447219],"iteration":2,"passed_time":0.1552474765,"remaining_time":51.59391136},
{"learn":[13.52213952],"iteration":3,"passed_time":0.1568342888,"remaining_time":39.0517379},
{"learn":[13.24168716],"iteration":4,"passed_time":0.1578279435,"remaining_time":31.40776076},
{"learn":[12.91646466],"iteration":5,"passed_time":0.1590545551,"remaining_time":26.35003796},
{"learn":[12.63834503],"iteration":6,"passed_time":0.1602845944,"remaining_time":22.7375146},
{"learn":[12.355835],"iteration":7,"passed_time":0.1615338257,"remaining_time":20.03019439},
{"learn":[12.0539591],"iteration":8,"passed_time":0.1624391018,"remaining_time":17.88634998},
{"learn":[11.7965486],"iteration":9,"passed_time":0.1637666192,"remaining_time":16.2128953},
{"learn":[11.55045134],"iteration":10,"passed_time":0.165033168,"remaining_time":14.83798211},
{"learn":[11.29904352],"iteration":11,"passed_time":0.1675093837,"remaining_time":13.79160592},
{"learn":[11.05277389],"iteration":12,"passed_time":0.168911187,"remaining_time":12.82425704},
{"learn":[10.82778779],"iteration":13,"passed_time":0.1701430958,"remaining_time":11.98293518},
{"learn":[10.60696162],"iteration":14,"passed_time":0.1714407108,"remaining_time":11.25794001},
{"learn":[10.38128571],"iteration":15,"passed_time":0.1727741535,"remaining_time":10.62561044},
{"learn":[10.16764569],"iteration":16,"passed_time":0.1741411792,"remaining_time":10.0694576},
{"learn":[9.981773593],"iteration":17,"passed_time":0.1751331776,"remaining_time":9.554487799},
{"learn":[9.821443852],"iteration":18,"passed_time":0.176241413,"remaining_time":9.09962243},
{"learn":[9.623455567],"iteration":19,"passed_time":0.177401558,"remaining_time":8.69267634},
{"learn":[9.454823763],"iteration":20,"passed_time":0.1788395433,"remaining_time":8.337329187},
{"learn":[9.282997447],"iteration":21,"passed_time":0.1809232581,"remaining_time":8.042861202},
{"learn":[9.128004642],"iteration":22,"passed_time":0.1821993589,"remaining_time":7.739511896},
{"learn":[8.976743055],"iteration":23,"passed_time":0.1834246725,"remaining_time":7.459270017},
{"learn":[8.836217736],"iteration":24,"passed_time":0.1842750949,"remaining_time":7.186728702},
{"learn":[8.687032251],"iteration":25,"passed_time":0.1854609709,"remaining_time":6.947653294},
{"learn":[8.556076327],"iteration":26,"passed_time":0.1865947451,"remaining_time":6.72432174},
{"learn":[8.415273979],"iteration":27,"passed_time":0.1878320755,"remaining_time":6.520456337},
{"learn":[8.282181408],"iteration":28,"passed_time":0.1890276714,"remaining_time":6.329167893},
{"learn":[8.180053115],"iteration":29,"passed_time":0.1904803759,"remaining_time":6.158865487},
{"learn":[8.048451816],"iteration":30,"passed_time":0.1915162883,"remaining_time":5.986428495},
{"learn":[7.93051256],"iteration":31,"passed_time":0.1932883152,"remaining_time":5.846971535},
{"learn":[7.823569904],"iteration":32,"passed_time":0.1953287691,"remaining_time":5.72372484},
{"learn":[7.740110678],"iteration":33,"passed_time":0.1967414315,"remaining_time":5.589771259},
{"learn":[7.639793924],"iteration":34,"passed_time":0.1980987424,"remaining_time":5.461865325},
{"learn":[7.557336824],"iteration":35,"passed_time":0.1993685703,"remaining_time":5.338647271},
{"learn":[7.453371438],"iteration":36,"passed_time":0.2010399801,"remaining_time":5.232472995},
{"learn":[7.36232998],"iteration":37,"passed_time":0.2019164609,"remaining_time":5.111674615},
{"learn":[7.26863831],"iteration":38,"passed_time":0.2030363899,"remaining_time":5.003024889},
{"learn":[7.192331778],"iteration":39,"passed_time":0.2039790343,"remaining_time":4.895496822},
{"learn":[7.105847359],"iteration":40,"passed_time":0.2051331574,"remaining_time":4.798114584},
{"learn":[7.032684313],"iteration":41,"passed_time":0.2069689108,"remaining_time":4.720862298},
{"learn":[6.960802672],"iteration":42,"passed_time":0.2093481368,"remaining_time":4.659213185},
{"learn":[6.890728969],"iteration":43,"passed_time":0.2106744093,"remaining_time":4.577380348},
{"learn":[6.827249663],"iteration":44,"passed_time":0.2116821989,"remaining_time":4.492366666},
{"learn":[6.755770042],"iteration":45,"passed_time":0.2126898441,"remaining_time":4.411002419},
{"learn":[6.695824749],"iteration":46,"passed_time":0.2138755715,"remaining_time":4.336668502},
{"learn":[6.64419212],"iteration":47,"passed_time":0.2148623162,"remaining_time":4.261435938},
{"learn":[6.580571077],"iteration":48,"passed_time":0.2158847612,"remaining_time":4.189926691},
{"learn":[6.52479093],"iteration":49,"passed_time":0.2169182071,"remaining_time":4.121445934},
{"learn":[6.479021744],"iteration":50,"passed_time":0.2180688655,"remaining_time":4.057791243},
{"learn":[6.422185718],"iteration":51,"passed_time":0.2191408316,"remaining_time":3.995105929},
{"learn":[6.373231],"iteration":52,"passed_time":0.2201780704,"remaining_time":3.934125144},
{"learn":[6.322942897],"iteration":53,"passed_time":0.2213553355,"remaining_time":3.877817544},
{"learn":[6.281481015],"iteration":54,"passed_time":0.2230666716,"remaining_time":3.832690994},
{"learn":[6.232555499],"iteration":55,"passed_time":0.224551139,"remaining_time":3.785290629},
{"learn":[6.185736794],"iteration":56,"passed_time":0.2261854089,"remaining_time":3.741979659},
{"learn":[6.151322383],"iteration":57,"passed_time":0.228869841,"remaining_time":3.7171619},
{"learn":[6.113709895],"iteration":58,"passed_time":0.2306736669,"remaining_time":3.6790495},
{"learn":[6.076592468],"iteration":59,"passed_time":0.2318909473,"remaining_time":3.632958174},
{"learn":[6.039994508],"iteration":60,"passed_time":0.2330656586,"remaining_time":3.587682843},
{"learn":[6.003135723],"iteration":61,"passed_time":0.2358894134,"remaining_time":3.568778545},
{"learn":[5.970818784],"iteration":62,"passed_time":0.2384749301,"remaining_time":3.546841421},
{"learn":[5.936729886],"iteration":63,"passed_time":0.2402271538,"remaining_time":3.513322124},
{"learn":[5.906455916],"iteration":64,"passed_time":0.2417165458,"remaining_time":3.476999543},
{"learn":[5.877574418],"iteration":65,"passed_time":0.243136527,"remaining_time":3.440750246},
{"learn":[5.852687052],"iteration":66,"passed_time":0.2445626711,"remaining_time":3.40562645},
{"learn":[5.823133413],"iteration":67,"passed_time":0.2464028604,"remaining_time":3.377168617},
{"learn":[5.796734721],"iteration":68,"passed_time":0.247947703,"remaining_time":3.345497268},
{"learn":[5.771171075],"iteration":69,"passed_time":0.25109018,"remaining_time":3.335912391},
{"learn":[5.744769448],"iteration":70,"passed_time":0.2529389878,"remaining_time":3.309581967},
{"learn":[5.7227015],"iteration":71,"passed_time":0.2540652685,"remaining_time":3.274619016},
{"learn":[5.699132028],"iteration":72,"passed_time":0.2553187016,"remaining_time":3.242197759},
{"learn":[5.680566822],"iteration":73,"passed_time":0.2566105398,"remaining_time":3.211099458},
{"learn":[5.658944519],"iteration":74,"passed_time":0.2576252395,"remaining_time":3.177377953},
{"learn":[5.636712451],"iteration":75,"passed_time":0.25915214,"remaining_time":3.150744439},
{"learn":[5.6203952],"iteration":76,"passed_time":0.2611630011,"remaining_time":3.130564286},
{"learn":[5.602472926],"iteration":77,"passed_time":0.2651014599,"remaining_time":3.133635205},
{"learn":[5.583793493],"iteration":78,"passed_time":0.2664459606,"remaining_time":3.106287718},
{"learn":[5.563283945],"iteration":79,"passed_time":0.2680298128,"remaining_time":3.082342847},
{"learn":[5.545923716],"iteration":80,"passed_time":0.269569468,"remaining_time":3.058448656},
{"learn":[5.531454163],"iteration":81,"passed_time":0.2704681262,"remaining_time":3.027923657},
{"learn":[5.514577358],"iteration":82,"passed_time":0.2715858708,"remaining_time":3.000533054},
{"learn":[5.501012862],"iteration":83,"passed_time":0.2726541438,"remaining_time":2.973228521},
{"learn":[5.485672786],"iteration":84,"passed_time":0.2736531303,"remaining_time":2.945795461},
{"learn":[5.470131432],"iteration":85,"passed_time":0.2747198804,"remaining_time":2.919697334},
{"learn":[5.456940983],"iteration":86,"passed_time":0.2770520125,"remaining_time":2.907453878},
{"learn":[5.445624251],"iteration":87,"passed_time":0.2798449447,"remaining_time":2.900211245},
{"learn":[5.436727388],"iteration":88,"passed_time":0.2813171091,"remaining_time":2.879549285},
{"learn":[5.421192856],"iteration":89,"passed_time":0.2822285857,"remaining_time":2.853644589},
{"learn":[5.407415063],"iteration":90,"passed_time":0.2832592378,"remaining_time":2.829479639},
{"learn":[5.398142674],"iteration":91,"passed_time":0.2844343495,"remaining_time":2.807243362},
{"learn":[5.387017845],"iteration":92,"passed_time":0.2856007035,"remaining_time":2.785374603},
{"learn":[5.375444154],"iteration":93,"passed_time":0.2866843765,"remaining_time":2.763149416},
{"learn":[5.365294582],"iteration":94,"passed_time":0.2883497997,"remaining_time":2.74691125},
{"learn":[5.352022587],"iteration":95,"passed_time":0.2908447138,"remaining_time":2.738787722},
{"learn":[5.343251324],"iteration":96,"passed_time":0.2931117837,"remaining_time":2.728659183},
{"learn":[5.333772633],"iteration":97,"passed_time":0.2948148775,"remaining_time":2.713500199},
{"learn":[5.324104868],"iteration":98,"passed_time":0.2960463163,"remaining_time":2.694320515},
{"learn":[5.311925446],"iteration":99,"passed_time":0.2970268419,"remaining_time":2.673241577},
{"learn":[5.297337091],"iteration":100,"passed_time":0.298278429,"remaining_time":2.654973343},
{"learn":[5.286710946],"iteration":101,"passed_time":0.3000673771,"remaining_time":2.641769653},
{"learn":[5.275903705],"iteration":102,"passed_time":0.301213644,"remaining_time":2.623190667},
{"learn":[5.268337441],"iteration":103,"passed_time":0.3027028321,"remaining_time":2.607901322},
{"learn":[5.260986072],"iteration":104,"passed_time":0.3050546372,"remaining_time":2.600227622},
{"learn":[5.248152407],"iteration":105,"passed_time":0.3100087442,"remaining_time":2.61460205},
{"learn":[5.23879065],"iteration":106,"passed_time":0.3118333085,"remaining_time":2.602496678},
{"learn":[5.228497283],"iteration":107,"passed_time":0.3133865345,"remaining_time":2.588340637},
{"learn":[5.215256513],"iteration":108,"passed_time":0.3146773997,"remaining_time":2.572271222},
{"learn":[5.205863212],"iteration":109,"passed_time":0.3159990834,"remaining_time":2.556719857},
{"learn":[5.198667759],"iteration":110,"passed_time":0.3172647163,"remaining_time":2.540975971},
{"learn":[5.187123639],"iteration":111,"passed_time":0.3195436645,"remaining_time":2.533524768},
{"learn":[5.175756333],"iteration":112,"passed_time":0.322447716,"remaining_time":2.531071895},
{"learn":[5.173617463],"iteration":113,"passed_time":0.3231975138,"remaining_time":2.511868396},
{"learn":[5.163043565],"iteration":114,"passed_time":0.3274846072,"remaining_time":2.52020763},
{"learn":[5.154468005],"iteration":115,"passed_time":0.3289497743,"remaining_time":2.506824142},
{"learn":[5.149143529],"iteration":116,"passed_time":0.3315386029,"remaining_time":2.502124669},
{"learn":[5.143390212],"iteration":117,"passed_time":0.3398971681,"remaining_time":2.540587307},
{"learn":[5.133551398],"iteration":118,"passed_time":0.3424703422,"remaining_time":2.535431693},
{"learn":[5.128081947],"iteration":119,"passed_time":0.3435107745,"remaining_time":2.519079013},
{"learn":[5.124004892],"iteration":120,"passed_time":0.3516043875,"remaining_time":2.554216997},
{"learn":[5.119271477],"iteration":121,"passed_time":0.3533623627,"remaining_time":2.543050446},
{"learn":[5.112267989],"iteration":122,"passed_time":0.3552931688,"remaining_time":2.53326918},
{"learn":[5.105098584],"iteration":123,"passed_time":0.3569451985,"remaining_time":2.521645112},
{"learn":[5.097473753],"iteration":124,"passed_time":0.3588380731,"remaining_time":2.511866512},
{"learn":[5.090547222],"iteration":125,"passed_time":0.3622411763,"remaining_time":2.512688795},
{"learn":[5.084769219],"iteration":126,"passed_time":0.3649705651,"remaining_time":2.508813412},
{"learn":[5.077546634],"iteration":127,"passed_time":0.3666130714,"remaining_time":2.497551549},
{"learn":[5.072635408],"iteration":128,"passed_time":0.3681523354,"remaining_time":2.485741737},
{"learn":[5.068649995],"iteration":129,"passed_time":0.3701902666,"remaining_time":2.477427169},
{"learn":[5.061727758],"iteration":130,"passed_time":0.3720110817,"remaining_time":2.467768168},
{"learn":[5.057361471],"iteration":131,"passed_time":0.3741505937,"remaining_time":2.460323601},
{"learn":[5.054024924],"iteration":132,"passed_time":0.377127917,"remaining_time":2.458420331},
{"learn":[5.050355178],"iteration":133,"passed_time":0.3785900442,"remaining_time":2.446708793},
{"learn":[5.045960768],"iteration":134,"passed_time":0.3798250081,"remaining_time":2.43369357},
{"learn":[5.041746923],"iteration":135,"passed_time":0.3809009324,"remaining_time":2.419841218},
{"learn":[5.035479717],"iteration":136,"passed_time":0.3819929535,"remaining_time":2.40627678},
{"learn":[5.029374824],"iteration":137,"passed_time":0.3830062142,"remaining_time":2.392401135},
{"learn":[5.019783278],"iteration":138,"passed_time":0.3840606563,"remaining_time":2.378965648},
{"learn":[5.011825366],"iteration":139,"passed_time":0.3851365185,"remaining_time":2.365838614},
{"learn":[5.004390322],"iteration":140,"passed_time":0.386504466,"remaining_time":2.35466196},
{"learn":[4.997723509],"iteration":141,"passed_time":0.3883578399,"remaining_time":2.346556525},
{"learn":[4.990668465],"iteration":142,"passed_time":0.3894872772,"remaining_time":2.334199976},
{"learn":[4.98694349],"iteration":143,"passed_time":0.3905981101,"remaining_time":2.321888765},
{"learn":[4.982747523],"iteration":144,"passed_time":0.391632246,"remaining_time":2.309279796},
{"learn":[4.979692713],"iteration":145,"passed_time":0.3926412,"remaining_time":2.296682088},
{"learn":[4.971169312],"iteration":146,"passed_time":0.3936785984,"remaining_time":2.284407105},
{"learn":[4.96474469],"iteration":147,"passed_time":0.3946537444,"remaining_time":2.27192561},
{"learn":[4.95921321],"iteration":148,"passed_time":0.3957429263,"remaining_time":2.260249868},
{"learn":[4.955872826],"iteration":149,"passed_time":0.3967743641,"remaining_time":2.248388063},
{"learn":[4.949345318],"iteration":150,"passed_time":0.397981651,"remaining_time":2.237658422},
{"learn":[4.946285901],"iteration":151,"passed_time":0.3990696172,"remaining_time":2.226388391},
{"learn":[4.940635333],"iteration":152,"passed_time":0.4010138464,"remaining_time":2.219991685},
{"learn":[4.933836065],"iteration":153,"passed_time":0.4027906568,"remaining_time":2.212733089},
{"learn":[4.928898227],"iteration":154,"passed_time":0.4040279663,"remaining_time":2.202604074},
{"learn":[4.926643513],"iteration":155,"passed_time":0.4052231675,"remaining_time":2.19236124},
{"learn":[4.922509414],"iteration":156,"passed_time":0.4062307179,"remaining_time":2.181226084},
{"learn":[4.915010171],"iteration":157,"passed_time":0.4074101397,"remaining_time":2.171135048},
{"learn":[4.913869671],"iteration":158,"passed_time":0.4082819578,"remaining_time":2.159529098},
{"learn":[4.907731462],"iteration":159,"passed_time":0.4094553545,"remaining_time":2.149640611},
{"learn":[4.901726142],"iteration":160,"passed_time":0.4105087832,"remaining_time":2.139235212},
{"learn":[4.897268329],"iteration":161,"passed_time":0.4116834912,"remaining_time":2.129572627},
{"learn":[4.896468432],"iteration":162,"passed_time":0.4123461795,"remaining_time":2.117384983},
{"learn":[4.894257145],"iteration":163,"passed_time":0.4143199368,"remaining_time":2.112021141},
{"learn":[4.891619204],"iteration":164,"passed_time":0.4326727231,"remaining_time":2.189586205},
{"learn":[4.887264817],"iteration":165,"passed_time":0.4341191178,"remaining_time":2.181056291},
{"learn":[4.883470878],"iteration":166,"passed_time":0.4353182044,"remaining_time":2.17137763},
{"learn":[4.880638752],"iteration":167,"passed_time":0.4366405529,"remaining_time":2.162410357},
{"learn":[4.875586706],"iteration":168,"passed_time":0.437771702,"remaining_time":2.152593399},
{"learn":[4.871509222],"iteration":169,"passed_time":0.4389953106,"remaining_time":2.143330046},
{"learn":[4.866707291],"iteration":170,"passed_time":0.4402033799,"remaining_time":2.134085392},
{"learn":[4.865639498],"iteration":171,"passed_time":0.4414214159,"remaining_time":2.124982165},
{"learn":[4.862243825],"iteration":172,"passed_time":0.4426740968,"remaining_time":2.116135711},
{"learn":[4.855083967],"iteration":173,"passed_time":0.4471253231,"remaining_time":2.122560442},
{"learn":[4.848219518],"iteration":174,"passed_time":0.4483744655,"remaining_time":2.113765337},
{"learn":[4.841097401],"iteration":175,"passed_time":0.4498086655,"remaining_time":2.105922388},
{"learn":[4.837966199],"iteration":176,"passed_time":0.4514640591,"remaining_time":2.099180343},
{"learn":[4.833598503],"iteration":177,"passed_time":0.4531246711,"remaining_time":2.092519549},
{"learn":[4.829973637],"iteration":178,"passed_time":0.4546931854,"remaining_time":2.085492208},
{"learn":[4.825257261],"iteration":179,"passed_time":0.4560194461,"remaining_time":2.077421921},
{"learn":[4.821656609],"iteration":180,"passed_time":0.4601576019,"remaining_time":2.082149591},
{"learn":[4.817270723],"iteration":181,"passed_time":0.4621490569,"remaining_time":2.077131476},
{"learn":[4.812010276],"iteration":182,"passed_time":0.4635846866,"remaining_time":2.069664967},
{"learn":[4.807776266],"iteration":183,"passed_time":0.4649925646,"remaining_time":2.062140939},
{"learn":[4.805608004],"iteration":184,"passed_time":0.4663171933,"remaining_time":2.054316284},
{"learn":[4.8041886],"iteration":185,"passed_time":0.4676638542,"remaining_time":2.046657942},
{"learn":[4.800219949],"iteration":186,"passed_time":0.4687320004,"remaining_time":2.037856237},
{"learn":[4.795982144],"iteration":187,"passed_time":0.4698535497,"remaining_time":2.029367459},
{"learn":[4.792252464],"iteration":188,"passed_time":0.4710299182,"remaining_time":2.021191871},
{"learn":[4.789515991],"iteration":189,"passed_time":0.472781351,"remaining_time":2.015541549},
{"learn":[4.786404855],"iteration":190,"passed_time":0.4748526058,"remaining_time":2.011286691},
{"learn":[4.777359584],"iteration":191,"passed_time":0.4760297433,"remaining_time":2.003291836},
{"learn":[4.775986432],"iteration":192,"passed_time":0.477189539,"remaining_time":1.995295119},
{"learn":[4.772883525],"iteration":193,"passed_time":0.4782616116,"remaining_time":1.987004428},
{"learn":[4.770130831],"iteration":194,"passed_time":0.4791999577,"remaining_time":1.978235723},
{"learn":[4.76865211],"iteration":195,"passed_time":0.4801068405,"remaining_time":1.969417856},
{"learn":[4.762845903],"iteration":196,"passed_time":0.4811626804,"remaining_time":1.961287474},
{"learn":[4.757153126],"iteration":197,"passed_time":0.4822737333,"remaining_time":1.953452192},
{"learn":[4.753097349],"iteration":198,"passed_time":0.4832871425,"remaining_time":1.945291463},
{"learn":[4.750752247],"iteration":199,"passed_time":0.4843826426,"remaining_time":1.93753057},
{"learn":[4.743425913],"iteration":200,"passed_time":0.4857535645,"remaining_time":1.930930836},
{"learn":[4.739724929],"iteration":201,"passed_time":0.4874785871,"remaining_time":1.925781745},
{"learn":[4.736568947],"iteration":202,"passed_time":0.4885032148,"remaining_time":1.917916563},
{"learn":[4.732774142],"iteration":203,"passed_time":0.4894251619,"remaining_time":1.909717788},
{"learn":[4.730788724],"iteration":204,"passed_time":0.4903086333,"remaining_time":1.901440797},
{"learn":[4.724537546],"iteration":205,"passed_time":0.49121105,"remaining_time":1.89330861},
{"learn":[4.718778293],"iteration":206,"passed_time":0.4921462168,"remaining_time":1.885371739},
{"learn":[4.714250468],"iteration":207,"passed_time":0.4930530804,"remaining_time":1.877394421},
{"learn":[4.706413243],"iteration":208,"passed_time":0.4940268874,"remaining_time":1.869738124},
{"learn":[4.703392089],"iteration":209,"passed_time":0.4949692152,"remaining_time":1.862027048},
{"learn":[4.698827385],"iteration":210,"passed_time":0.4960662961,"remaining_time":1.854958804},
{"learn":[4.696074397],"iteration":211,"passed_time":0.4972178822,"remaining_time":1.848149487},
{"learn":[4.689957775],"iteration":212,"passed_time":0.4983868101,"remaining_time":1.841457369},
{"learn":[4.686625685],"iteration":213,"passed_time":0.4996401668,"remaining_time":1.835126968},
{"learn":[4.684367244],"iteration":214,"passed_time":0.5012691058,"remaining_time":1.830215107},
{"learn":[4.67988294],"iteration":215,"passed_time":0.5023922065,"remaining_time":1.823497638},
{"learn":[4.67773011],"iteration":216,"passed_time":0.5033359665,"remaining_time":1.816184617},
{"learn":[4.676073973],"iteration":217,"passed_time":0.5042936927,"remaining_time":1.808980127},
{"learn":[4.67321495],"iteration":218,"passed_time":0.5052059678,"remaining_time":1.801670597},
{"learn":[4.670006526],"iteration":219,"passed_time":0.5061385464,"remaining_time":1.79449121},
{"learn":[4.664451953],"iteration":220,"passed_time":0.5070540082,"remaining_time":1.78730802},
{"learn":[4.659753471],"iteration":221,"passed_time":0.5081237647,"remaining_time":1.780722022},
{"learn":[4.655715733],"iteration":222,"passed_time":0.5100411085,"remaining_time":1.77713875},
{"learn":[4.649960004],"iteration":223,"passed_time":0.511404055,"remaining_time":1.771649762},
{"learn":[4.648880919],"iteration":224,"passed_time":0.5123699101,"remaining_time":1.76482969},
{"learn":[4.645533626],"iteration":225,"passed_time":0.5139561196,"remaining_time":1.760186003},
{"learn":[4.640192222],"iteration":226,"passed_time":0.5156181806,"remaining_time":1.755827549},
{"learn":[4.638692103],"iteration":227,"passed_time":0.5166863286,"remaining_time":1.749481779},
{"learn":[4.635309901],"iteration":228,"passed_time":0.5176267852,"remaining_time":1.742752189},
{"learn":[4.630496135],"iteration":229,"passed_time":0.5186216371,"remaining_time":1.736255046},
{"learn":[4.628090804],"iteration":230,"passed_time":0.5195160179,"remaining_time":1.729471073},
{"learn":[4.625263205],"iteration":231,"passed_time":0.5205011626,"remaining_time":1.723038331},
{"learn":[4.621560816],"iteration":232,"passed_time":0.5215374628,"remaining_time":1.716820747},
{"learn":[4.620282416],"iteration":233,"passed_time":0.5225493467,"remaining_time":1.71056752},
{"learn":[4.617633972],"iteration":234,"passed_time":0.5241921325,"remaining_time":1.706412687},
{"learn":[4.614337985],"iteration":235,"passed_time":0.5251720478,"remaining_time":1.70013324},
{"learn":[4.611387762],"iteration":236,"passed_time":0.5260675125,"remaining_time":1.693626633},
{"learn":[4.607067311],"iteration":237,"passed_time":0.527299863,"remaining_time":1.68824578},
{"learn":[4.605719502],"iteration":238,"passed_time":0.5291074835,"remaining_time":1.68473136},
{"learn":[4.602510018],"iteration":239,"passed_time":0.5302649386,"remaining_time":1.679172306},
{"learn":[4.598541336],"iteration":240,"passed_time":0.5312494469,"remaining_time":1.673105105},
{"learn":[4.596959083],"iteration":241,"passed_time":0.5321511575,"remaining_time":1.666820568},
{"learn":[4.594736357],"iteration":242,"passed_time":0.5330894406,"remaining_time":1.660694266},
{"learn":[4.590601739],"iteration":243,"passed_time":0.5340800001,"remaining_time":1.654772459},
{"learn":[4.589673496],"iteration":244,"passed_time":0.5351308256,"remaining_time":1.649076626},
{"learn":[4.585454427],"iteration":245,"passed_time":0.5361828071,"remaining_time":1.6434221},
{"learn":[4.581450524],"iteration":246,"passed_time":0.5371698683,"remaining_time":1.637606926},
{"learn":[4.576674882],"iteration":247,"passed_time":0.5381006764,"remaining_time":1.631660115},
{"learn":[4.572753362],"iteration":248,"passed_time":0.539018038,"remaining_time":1.625713038},
{"learn":[4.568572728],"iteration":249,"passed_time":0.5399370896,"remaining_time":1.619811269},
{"learn":[4.559409626],"iteration":250,"passed_time":0.5411857711,"remaining_time":1.614932839},
{"learn":[4.5512087],"iteration":251,"passed_time":0.5430268159,"remaining_time":1.611841501},
{"learn":[4.549311276],"iteration":252,"passed_time":0.5442473536,"remaining_time":1.606927957},
{"learn":[4.545955332],"iteration":253,"passed_time":0.5452110487,"remaining_time":1.601289143},
{"learn":[4.541931224],"iteration":254,"passed_time":0.5461851756,"remaining_time":1.595717474},
{"learn":[4.537715798],"iteration":255,"passed_time":0.5472702237,"remaining_time":1.590504088},
{"learn":[4.535201579],"iteration":256,"passed_time":0.5482697257,"remaining_time":1.58507551},
{"learn":[4.528152839],"iteration":257,"passed_time":0.5493402083,"remaining_time":1.579885405},
{"learn":[4.524281834],"iteration":258,"passed_time":0.550267932,"remaining_time":1.574318678},
{"learn":[4.522935216],"iteration":259,"passed_time":0.5511975346,"remaining_time":1.568792983},
{"learn":[4.517636273],"iteration":260,"passed_time":0.5521264378,"remaining_time":1.563300527},
{"learn":[4.512497407],"iteration":261,"passed_time":0.5530355555,"remaining_time":1.557787175},
{"learn":[4.508591506],"iteration":262,"passed_time":0.5541154515,"remaining_time":1.552787406},
{"learn":[4.505797247],"iteration":263,"passed_time":0.5554207161,"remaining_time":1.548445633},
{"learn":[4.501371787],"iteration":264,"passed_time":0.5574944138,"remaining_time":1.546258091},
{"learn":[4.497244608],"iteration":265,"passed_time":0.5585694566,"remaining_time":1.541315719},
{"learn":[4.492216169],"iteration":266,"passed_time":0.5594931709,"remaining_time":1.53598687},
{"learn":[4.489678053],"iteration":267,"passed_time":0.5604478303,"remaining_time":1.530775417},
{"learn":[4.48728963],"iteration":268,"passed_time":0.5615531678,"remaining_time":1.526005077},
{"learn":[4.485642786],"iteration":269,"passed_time":0.5625616172,"remaining_time":1.520999928},
{"learn":[4.481402815],"iteration":270,"passed_time":0.5635436582,"remaining_time":1.515953235},
{"learn":[4.476874608],"iteration":271,"passed_time":0.5645346794,"remaining_time":1.510960465},
{"learn":[4.470747168],"iteration":272,"passed_time":0.5656296405,"remaining_time":1.506273804},
{"learn":[4.468777468],"iteration":273,"passed_time":0.5665449587,"remaining_time":1.501137372},
{"learn":[4.468467483],"iteration":274,"passed_time":0.5674549302,"remaining_time":1.496017543},
{"learn":[4.466159008],"iteration":275,"passed_time":0.5689230834,"remaining_time":1.492392436},
{"learn":[4.465371604],"iteration":276,"passed_time":0.5704978319,"remaining_time":1.489061128},
{"learn":[4.46419507],"iteration":277,"passed_time":0.5715347626,"remaining_time":1.484345678},
{"learn":[4.459105366],"iteration":278,"passed_time":0.5725044359,"remaining_time":1.479482789},
{"learn":[4.455810525],"iteration":279,"passed_time":0.5734866489,"remaining_time":1.474679954},
{"learn":[4.447802508],"iteration":280,"passed_time":0.5745300128,"remaining_time":1.47006078},
{"learn":[4.446151371],"iteration":281,"passed_time":0.5756420966,"remaining_time":1.465641934},
{"learn":[4.44389729],"iteration":282,"passed_time":0.5766223309,"remaining_time":1.460912407},
{"learn":[4.438754686],"iteration":283,"passed_time":0.5776382495,"remaining_time":1.456299249},
{"learn":[4.435975385],"iteration":284,"passed_time":0.5786175889,"remaining_time":1.451619565},
{"learn":[4.434702455],"iteration":285,"passed_time":0.5795593308,"remaining_time":1.446871896},
{"learn":[4.433582603],"iteration":286,"passed_time":0.5805294624,"remaining_time":1.442221278},
{"learn":[4.431396059],"iteration":287,"passed_time":0.5814915398,"remaining_time":1.437576307},
{"learn":[4.427367066],"iteration":288,"passed_time":0.5827492468,"remaining_time":1.433684133},
{"learn":[4.425952909],"iteration":289,"passed_time":0.5845347026,"remaining_time":1.431102203},
{"learn":[4.424865242],"iteration":290,"passed_time":0.5856783948,"remaining_time":1.426962137},
{"learn":[4.420603807],"iteration":291,"passed_time":0.5867303485,"remaining_time":1.42262016},
{"learn":[4.41447669],"iteration":292,"passed_time":0.5877519834,"remaining_time":1.418227482},
{"learn":[4.410563878],"iteration":293,"passed_time":0.5887088474,"remaining_time":1.413702198},
{"learn":[4.407778526],"iteration":294,"passed_time":0.5897144836,"remaining_time":1.409317664},
{"learn":[4.404966875],"iteration":295,"passed_time":0.5906511062,"remaining_time":1.40479182},
{"learn":[4.400573883],"iteration":296,"passed_time":0.5916317393,"remaining_time":1.400394319},
{"learn":[4.392790513],"iteration":297,"passed_time":0.5925564869,"remaining_time":1.3958881},
{"learn":[4.391369633],"iteration":298,"passed_time":0.59357506,"remaining_time":1.39162581},
{"learn":[4.389931187],"iteration":299,"passed_time":0.5945413988,"remaining_time":1.387263264},
{"learn":[4.386057467],"iteration":300,"passed_time":0.5956660676,"remaining_time":1.383290968},
{"learn":[4.384617705],"iteration":301,"passed_time":0.5971674966,"remaining_time":1.38020832},
{"learn":[4.384005596],"iteration":302,"passed_time":0.5988575914,"remaining_time":1.377570103},
{"learn":[4.381284129],"iteration":303,"passed_time":0.599873243,"remaining_time":1.373394004},
{"learn":[4.379772766],"iteration":304,"passed_time":0.6008550481,"remaining_time":1.369161503},
{"learn":[4.376291376],"iteration":305,"passed_time":0.6018179809,"remaining_time":1.364907447},
{"learn":[4.371870715],"iteration":306,"passed_time":0.602791756,"remaining_time":1.360699306},
{"learn":[4.368201633],"iteration":307,"passed_time":0.6037396297,"remaining_time":1.356453973},
{"learn":[4.367981089],"iteration":308,"passed_time":0.6046639282,"remaining_time":1.352177263},
{"learn":[4.365460406],"iteration":309,"passed_time":0.6056306414,"remaining_time":1.348016589},
{"learn":[4.359481557],"iteration":310,"passed_time":0.6065823751,"remaining_time":1.343843268},
{"learn":[4.356586524],"iteration":311,"passed_time":0.6075844955,"remaining_time":1.339801708},
{"learn":[4.352152851],"iteration":312,"passed_time":0.6089642465,"remaining_time":1.336608426},
{"learn":[4.350696251],"iteration":313,"passed_time":0.6105958316,"remaining_time":1.33397688},
{"learn":[4.348280664],"iteration":314,"passed_time":0.6127202996,"remaining_time":1.332423509},
{"learn":[4.344689229],"iteration":315,"passed_time":0.6141172136,"remaining_time":1.32929169},
{"learn":[4.342417363],"iteration":316,"passed_time":0.6153698953,"remaining_time":1.325860058},
{"learn":[4.338835334],"iteration":317,"passed_time":0.6165337064,"remaining_time":1.322251534},
{"learn":[4.335498497],"iteration":318,"passed_time":0.6176986492,"remaining_time":1.318660753},
{"learn":[4.330547834],"iteration":319,"passed_time":0.618810785,"remaining_time":1.314972918},
{"learn":[4.32814857],"iteration":320,"passed_time":0.6200372471,"remaining_time":1.311542962},
{"learn":[4.32480018],"iteration":321,"passed_time":0.6213028313,"remaining_time":1.308209067},
{"learn":[4.322026145],"iteration":322,"passed_time":0.6221769329,"remaining_time":1.304067441},
{"learn":[4.319846797],"iteration":323,"passed_time":0.6231617728,"remaining_time":1.300177032},
{"learn":[4.317844445],"iteration":324,"passed_time":0.6250579785,"remaining_time":1.29819734},
{"learn":[4.313966526],"iteration":325,"passed_time":0.6269127175,"remaining_time":1.296132428},
{"learn":[4.313011708],"iteration":326,"passed_time":0.6281614292,"remaining_time":1.292821535},
{"learn":[4.310707958],"iteration":327,"passed_time":0.629268454,"remaining_time":1.28923293},
{"learn":[4.308760966],"iteration":328,"passed_time":0.6305649196,"remaining_time":1.286045778},
{"learn":[4.305911246],"iteration":329,"passed_time":0.6318167745,"remaining_time":1.282779512},
{"learn":[4.302381154],"iteration":330,"passed_time":0.6327679701,"remaining_time":1.27891774},
{"learn":[4.301885868],"iteration":331,"passed_time":0.633708326,"remaining_time":1.275051692},
{"learn":[4.299849717],"iteration":332,"passed_time":0.6351483631,"remaining_time":1.272204079},
{"learn":[4.297201793],"iteration":333,"passed_time":0.6364286035,"remaining_time":1.269046257},
{"learn":[4.296106068],"iteration":334,"passed_time":0.6381230931,"remaining_time":1.266721961},
{"learn":[4.294017538],"iteration":335,"passed_time":0.6398878104,"remaining_time":1.264540197},
{"learn":[4.289622776],"iteration":336,"passed_time":0.6410043478,"remaining_time":1.261085705},
{"learn":[4.287354473],"iteration":337,"passed_time":0.6423917694,"remaining_time":1.258175596},
{"learn":[4.286383798],"iteration":338,"passed_time":0.6433481524,"remaining_time":1.254434008},
{"learn":[4.28392239],"iteration":339,"passed_time":0.6445843537,"remaining_time":1.251251981},
{"learn":[4.283753761],"iteration":340,"passed_time":0.6454245063,"remaining_time":1.247315981},
{"learn":[4.27933377],"iteration":341,"passed_time":0.6461995473,"remaining_time":1.243272813},
{"learn":[4.27590205],"iteration":342,"passed_time":0.6470337067,"remaining_time":1.23936194},
{"learn":[4.273905875],"iteration":343,"passed_time":0.6479403394,"remaining_time":1.235607159},
{"learn":[4.269768675],"iteration":344,"passed_time":0.6491033244,"remaining_time":1.232355587},
{"learn":[4.265053571],"iteration":345,"passed_time":0.6500264325,"remaining_time":1.228662679},
{"learn":[4.260262727],"iteration":346,"passed_time":0.6511040367,"remaining_time":1.225276472},
{"learn":[4.253559529],"iteration":347,"passed_time":0.6533142356,"remaining_time":1.224025522},
{"learn":[4.251035897],"iteration":348,"passed_time":0.6549075389,"remaining_time":1.221618361},
{"learn":[4.250850881],"iteration":349,"passed_time":0.6557915695,"remaining_time":1.217898629},
{"learn":[4.24731417],"iteration":350,"passed_time":0.6564749207,"remaining_time":1.213823999},
{"learn":[4.245339184],"iteration":351,"passed_time":0.6571485873,"remaining_time":1.209750809},
{"learn":[4.241057379],"iteration":352,"passed_time":0.6584528184,"remaining_time":1.206852616},
{"learn":[4.236620066],"iteration":353,"passed_time":0.6593177182,"remaining_time":1.203161712},
{"learn":[4.233428075],"iteration":354,"passed_time":0.6601611886,"remaining_time":1.199447793},
{"learn":[4.231093687],"iteration":355,"passed_time":0.6609362413,"remaining_time":1.195626234},
{"learn":[4.227780852],"iteration":356,"passed_time":0.6617207394,"remaining_time":1.191838755},
{"learn":[4.225590675],"iteration":357,"passed_time":0.6628200735,"remaining_time":1.188632646},
{"learn":[4.221941142],"iteration":358,"passed_time":0.6635959859,"remaining_time":1.184860799},
{"learn":[4.217437211],"iteration":359,"passed_time":0.6643478849,"remaining_time":1.181062906},
{"learn":[4.214412379],"iteration":360,"passed_time":0.6654495436,"remaining_time":1.177900993},
{"learn":[4.213067067],"iteration":361,"passed_time":0.6671186523,"remaining_time":1.175750553},
{"learn":[4.210412715],"iteration":362,"passed_time":0.6685078755,"remaining_time":1.173111616},
{"learn":[4.207731757],"iteration":363,"passed_time":0.6697093723,"remaining_time":1.170151541},
{"learn":[4.200212471],"iteration":364,"passed_time":0.6708130106,"remaining_time":1.167030854},
{"learn":[4.197507823],"iteration":365,"passed_time":0.67185736,"remaining_time":1.163818487},
{"learn":[4.195657345],"iteration":366,"passed_time":0.6727004677,"remaining_time":1.160270834},
{"learn":[4.193532234],"iteration":367,"passed_time":0.6737043746,"remaining_time":1.157014035},
{"learn":[4.187651745],"iteration":368,"passed_time":0.6746993214,"remaining_time":1.153754124},
{"learn":[4.183876464],"iteration":369,"passed_time":0.6754699222,"remaining_time":1.150124462},
{"learn":[4.180877994],"iteration":370,"passed_time":0.6764187974,"remaining_time":1.146812462},
{"learn":[4.178674614],"iteration":371,"passed_time":0.6775535681,"remaining_time":1.143826991},
{"learn":[4.173704657],"iteration":372,"passed_time":0.6796302041,"remaining_time":1.142434686},
{"learn":[4.169910348],"iteration":373,"passed_time":0.681497942,"remaining_time":1.140689069},
{"learn":[4.165577084],"iteration":374,"passed_time":0.6825883916,"remaining_time":1.137647319},
{"learn":[4.164515145],"iteration":375,"passed_time":0.6836456553,"remaining_time":1.134560875},
{"learn":[4.161687764],"iteration":376,"passed_time":0.6845697741,"remaining_time":1.131265171},
{"learn":[4.158659707],"iteration":377,"passed_time":0.6855847315,"remaining_time":1.128131489},
{"learn":[4.155271919],"iteration":378,"passed_time":0.6866778683,"remaining_time":1.125137088},
{"learn":[4.150303652],"iteration":379,"passed_time":0.6877330525,"remaining_time":1.12209077},
{"learn":[4.147825897],"iteration":380,"passed_time":0.688764717,"remaining_time":1.119016692},
{"learn":[4.143506338],"iteration":381,"passed_time":0.6907868956,"remaining_time":1.117555763},
{"learn":[4.137720887],"iteration":382,"passed_time":0.6926097801,"remaining_time":1.115770847},
{"learn":[4.135674392],"iteration":383,"passed_time":0.6952381252,"remaining_time":1.115277826},
{"learn":[4.131825072],"iteration":384,"passed_time":0.6966629706,"remaining_time":1.112851239},
{"learn":[4.127617336],"iteration":385,"passed_time":0.6979294161,"remaining_time":1.11017788},
{"learn":[4.126441364],"iteration":386,"passed_time":0.6990599952,"remaining_time":1.107296581},
{"learn":[4.12470876],"iteration":387,"passed_time":0.7001406678,"remaining_time":1.104345589},
{"learn":[4.122074677],"iteration":388,"passed_time":0.7014379939,"remaining_time":1.10174451},
{"learn":[4.115958782],"iteration":389,"passed_time":0.7026800693,"remaining_time":1.099063698},
{"learn":[4.112985731],"iteration":390,"passed_time":0.7037661794,"remaining_time":1.096147323},
{"learn":[4.109323047],"iteration":391,"passed_time":0.7047535865,"remaining_time":1.093087195},
{"learn":[4.105763246],"iteration":392,"passed_time":0.7058078053,"remaining_time":1.090140809},
{"learn":[4.101343792],"iteration":393,"passed_time":0.7072948223,"remaining_time":1.087869701},
{"learn":[4.099478146],"iteration":394,"passed_time":0.7091053483,"remaining_time":1.086098065},
{"learn":[4.09772429],"iteration":395,"passed_time":0.7100865406,"remaining_time":1.083061289},
{"learn":[4.094731741],"iteration":396,"passed_time":0.7113116074,"remaining_time":1.080405288},
{"learn":[4.093428152],"iteration":397,"passed_time":0.7121781828,"remaining_time":1.077214236},
{"learn":[4.089271701],"iteration":398,"passed_time":0.7131698244,"remaining_time":1.074223219},
{"learn":[4.087296283],"iteration":399,"passed_time":0.7142613813,"remaining_time":1.071392072},
{"learn":[4.083723559],"iteration":400,"passed_time":0.7157914972,"remaining_time":1.069224705},
{"learn":[4.081773675],"iteration":401,"passed_time":0.7171950702,"remaining_time":1.066872269},
{"learn":[4.078338262],"iteration":402,"passed_time":0.718738635,"remaining_time":1.064731923},
{"learn":[4.075110729],"iteration":403,"passed_time":0.7200255327,"remaining_time":1.062215885},
{"learn":[4.070787096],"iteration":404,"passed_time":0.7218453597,"remaining_time":1.060488862},
{"learn":[4.069932277],"iteration":405,"passed_time":0.7239440153,"remaining_time":1.059169323},
{"learn":[4.064835749],"iteration":406,"passed_time":0.7252534681,"remaining_time":1.056696085},
{"learn":[4.064292686],"iteration":407,"passed_time":0.7267469628,"remaining_time":1.054495593},
{"learn":[4.060464392],"iteration":408,"passed_time":0.7279109653,"remaining_time":1.051822446},
{"learn":[4.059910658],"iteration":409,"passed_time":0.7288722955,"remaining_time":1.048865011},
{"learn":[4.057523148],"iteration":410,"passed_time":0.7298862354,"remaining_time":1.045992683},
{"learn":[4.0559423],"iteration":411,"passed_time":0.730827393,"remaining_time":1.043025503},
{"learn":[4.051508125],"iteration":412,"passed_time":0.7318196768,"remaining_time":1.0401408},
{"learn":[4.050152915],"iteration":413,"passed_time":0.7329115787,"remaining_time":1.037406244},
{"learn":[4.047193108],"iteration":414,"passed_time":0.7339979222,"remaining_time":1.03467177},
{"learn":[4.041406639],"iteration":415,"passed_time":0.7359644202,"remaining_time":1.033180821},
{"learn":[4.03933998],"iteration":416,"passed_time":0.737407776,"remaining_time":1.030956195},
{"learn":[4.03618801],"iteration":417,"passed_time":0.7384759365,"remaining_time":1.028212907},
{"learn":[4.03187688],"iteration":418,"passed_time":0.7394609107,"remaining_time":1.025362265},
{"learn":[4.03028227],"iteration":419,"passed_time":0.7404975711,"remaining_time":1.022591884},
{"learn":[4.027195951],"iteration":420,"passed_time":0.7414629503,"remaining_time":1.019731706},
{"learn":[4.022589549],"iteration":421,"passed_time":0.7424489143,"remaining_time":1.016908702},
{"learn":[4.019564504],"iteration":422,"passed_time":0.743575221,"remaining_time":1.014285822},
{"learn":[4.017950191],"iteration":423,"passed_time":0.7449054576,"remaining_time":1.011947037},
{"learn":[4.014334803],"iteration":424,"passed_time":0.7459794284,"remaining_time":1.009266286},
{"learn":[4.011338415],"iteration":425,"passed_time":0.7470281291,"remaining_time":1.006559028},
{"learn":[4.008933824],"iteration":426,"passed_time":0.7484525765,"remaining_time":1.004363762},
{"learn":[4.008118431],"iteration":427,"passed_time":0.7505062049,"remaining_time":1.003012965},
{"learn":[4.006135011],"iteration":428,"passed_time":0.7518494867,"remaining_time":1.000713419},
{"learn":[4.005978131],"iteration":429,"passed_time":0.7530361669,"remaining_time":0.9982107329},
{"learn":[4.005088142],"iteration":430,"passed_time":0.7542044971,"remaining_time":0.9956899277},
{"learn":[4.0029674],"iteration":431,"passed_time":0.7552287361,"remaining_time":0.9929859308},
{"learn":[4.001239085],"iteration":432,"passed_time":0.7562159904,"remaining_time":0.9902412622},
{"learn":[3.996669311],"iteration":433,"passed_time":0.7574291664,"remaining_time":0.9877993276},
{"learn":[3.993730098],"iteration":434,"passed_time":0.7584437644,"remaining_time":0.9851051193},
{"learn":[3.991909812],"iteration":435,"passed_time":0.7594885933,"remaining_time":0.9824577216},
{"learn":[3.989107857],"iteration":436,"passed_time":0.760705574,"remaining_time":0.9800394466},
{"learn":[3.985074805],"iteration":437,"passed_time":0.7618764957,"remaining_time":0.9775675584},
{"learn":[3.98002669],"iteration":438,"passed_time":0.7637671246,"remaining_time":0.9760213141},
{"learn":[3.977103435],"iteration":439,"passed_time":0.7652338053,"remaining_time":0.973933934},
{"learn":[3.973632928],"iteration":440,"passed_time":0.7662980151,"remaining_time":0.9713392073},
{"learn":[3.970344957],"iteration":441,"passed_time":0.7674210587,"remaining_time":0.9688256804},
{"learn":[3.968692807],"iteration":442,"passed_time":0.7683896213,"remaining_time":0.9661241965},
{"learn":[3.965343423],"iteration":443,"passed_time":0.769422069,"remaining_time":0.9635105188},
{"learn":[3.964677385],"iteration":444,"passed_time":0.7704475177,"remaining_time":0.9608952187},
{"learn":[3.964531171],"iteration":445,"passed_time":0.771427292,"remaining_time":0.9582303134},
{"learn":[3.96370309],"iteration":446,"passed_time":0.772385605,"remaining_time":0.9555463972},
{"learn":[3.962035241],"iteration":447,"passed_time":0.7733048874,"remaining_time":0.9528220934},
{"learn":[3.958679444],"iteration":448,"passed_time":0.7742809284,"remaining_time":0.9501754823},
{"learn":[3.956650651],"iteration":449,"passed_time":0.7753636712,"remaining_time":0.9476667093},
{"learn":[3.953919675],"iteration":450,"passed_time":0.7766536583,"remaining_time":0.9454165375},
{"learn":[3.950235929],"iteration":451,"passed_time":0.7784379606,"remaining_time":0.9437699168},
{"learn":[3.944023087],"iteration":452,"passed_time":0.7798127904,"remaining_time":0.941628248},
{"learn":[3.941792475],"iteration":453,"passed_time":0.7807725734,"remaining_time":0.9389908041},
{"learn":[3.938568703],"iteration":454,"passed_time":0.781765957,"remaining_time":0.9364009814},
{"learn":[3.935032517],"iteration":455,"passed_time":0.7827269942,"remaining_time":0.933779572},
{"learn":[3.932486166],"iteration":456,"passed_time":0.783756235,"remaining_time":0.9312464674},
{"learn":[3.929876542],"iteration":457,"passed_time":0.7847665246,"remaining_time":0.928697503},
{"learn":[3.929126339],"iteration":458,"passed_time":0.7857833776,"remaining_time":0.9261629788},
{"learn":[3.927192411],"iteration":459,"passed_time":0.7867377222,"remaining_time":0.9235616739},
{"learn":[3.925836664],"iteration":460,"passed_time":0.7877394371,"remaining_time":0.9210228994},
{"learn":[3.923678707],"iteration":461,"passed_time":0.788679097,"remaining_time":0.9184185156},
{"learn":[3.923552183],"iteration":462,"passed_time":0.7896726628,"remaining_time":0.9158838443},
{"learn":[3.919455187],"iteration":463,"passed_time":0.7913290143,"remaining_time":0.9141214475},
{"learn":[3.91733829],"iteration":464,"passed_time":0.7928519851,"remaining_time":0.9122060473},
{"learn":[3.915519747],"iteration":465,"passed_time":0.7938881409,"remaining_time":0.9097344791},
{"learn":[3.910066732],"iteration":466,"passed_time":0.7947859386,"remaining_time":0.9071111462},
{"learn":[3.906808877],"iteration":467,"passed_time":0.7958138471,"remaining_time":0.9046430911},
{"learn":[3.905057093],"iteration":468,"passed_time":0.7969517332,"remaining_time":0.9023056937},
{"learn":[3.903205707],"iteration":469,"passed_time":0.7980060082,"remaining_time":0.8998791157},
{"learn":[3.900410357],"iteration":470,"passed_time":0.7990122834,"remaining_time":0.8974044541},
{"learn":[3.896155308],"iteration":471,"passed_time":0.7999795162,"remaining_time":0.8948923401},
{"learn":[3.891422671],"iteration":472,"passed_time":0.8010017219,"remaining_time":0.8924480072},
{"learn":[3.887258879],"iteration":473,"passed_time":0.8019372127,"remaining_time":0.8899134471},
{"learn":[3.886485733],"iteration":474,"passed_time":0.8029241808,"remaining_time":0.8874425156},
{"learn":[3.885758998],"iteration":475,"passed_time":0.804285821,"remaining_time":0.8853902736},
{"learn":[3.884341563],"iteration":476,"passed_time":0.8070155103,"remaining_time":0.8848409054},
{"learn":[3.880171572],"iteration":477,"passed_time":0.8085688865,"remaining_time":0.8829978217},
{"learn":[3.878259205],"iteration":478,"passed_time":0.8098225471,"remaining_time":0.8808299521},
{"learn":[3.874995831],"iteration":479,"passed_time":0.8110429933,"remaining_time":0.8786299094},
{"learn":[3.873285231],"iteration":480,"passed_time":0.8122645065,"remaining_time":0.8764350913},
{"learn":[3.868284544],"iteration":481,"passed_time":0.8135069908,"remaining_time":0.874266849},
{"learn":[3.864561747],"iteration":482,"passed_time":0.8147830747,"remaining_time":0.872138405},
{"learn":[3.863251112],"iteration":483,"passed_time":0.8158949604,"remaining_time":0.8698384288},
{"learn":[3.860500658],"iteration":484,"passed_time":0.8170726687,"remaining_time":0.8676132462},
{"learn":[3.856552751],"iteration":485,"passed_time":0.8186192214,"remaining_time":0.8657824687},
{"learn":[3.856021058],"iteration":486,"passed_time":0.8205449729,"remaining_time":0.864352302},
{"learn":[3.8555208],"iteration":487,"passed_time":0.8217321366,"remaining_time":0.8621451925},
{"learn":[3.852415471],"iteration":488,"passed_time":0.823005744,"remaining_time":0.8600325873},
{"learn":[3.85227431],"iteration":489,"passed_time":0.8241356976,"remaining_time":0.8577738894},
{"learn":[3.846646115],"iteration":490,"passed_time":0.8252851472,"remaining_time":0.8555399998},
{"learn":[3.841613915],"iteration":491,"passed_time":0.8264764355,"remaining_time":0.8533537179},
{"learn":[3.839991621],"iteration":492,"passed_time":0.8277689856,"remaining_time":0.85127561},
{"learn":[3.835879894],"iteration":493,"passed_time":0.8288900874,"remaining_time":0.8490250693},
{"learn":[3.830611351],"iteration":494,"passed_time":0.8300965079,"remaining_time":0.8468661343},
{"learn":[3.828946066],"iteration":495,"passed_time":0.8311787076,"remaining_time":0.8445848158},
{"learn":[3.828822707],"iteration":496,"passed_time":0.8325101506,"remaining_time":0.8425605749},
{"learn":[3.8251739],"iteration":497,"passed_time":0.8345131447,"remaining_time":0.8412160615},
{"learn":[3.822645408],"iteration":498,"passed_time":0.8358041904,"remaining_time":0.839154107},
{"learn":[3.81892439],"iteration":499,"passed_time":0.8370200243,"remaining_time":0.8370200243},
{"learn":[3.817443775],"iteration":500,"passed_time":0.8379845707,"remaining_time":0.8346393229},
{"learn":[3.81587254],"iteration":501,"passed_time":0.8389736795,"remaining_time":0.8322886303},
{"learn":[3.815048834],"iteration":502,"passed_time":0.8400123799,"remaining_time":0.8299923515},
{"learn":[3.8149468],"iteration":503,"passed_time":0.8409703143,"remaining_time":0.8276215791},
{"learn":[3.812353469],"iteration":504,"passed_time":0.8421516485,"remaining_time":0.8254753782},
{"learn":[3.811014251],"iteration":505,"passed_time":0.843304216,"remaining_time":0.8233049065},
{"learn":[3.810859097],"iteration":506,"passed_time":0.8441217967,"remaining_time":0.8208127136},
{"learn":[3.809137616],"iteration":507,"passed_time":0.8451585209,"remaining_time":0.8185393549},
{"learn":[3.807520558],"iteration":508,"passed_time":0.848645613,"remaining_time":0.8186345697},
{"learn":[3.805159065],"iteration":509,"passed_time":0.8501067471,"remaining_time":0.8167692276},
{"learn":[3.802569354],"iteration":510,"passed_time":0.8513394074,"remaining_time":0.8146868301},
{"learn":[3.802003375],"iteration":511,"passed_time":0.8523768955,"remaining_time":0.8124217285},
{"learn":[3.800350925],"iteration":512,"passed_time":0.8535493536,"remaining_time":0.8102895423},
{"learn":[3.798789569],"iteration":513,"passed_time":0.8546131025,"remaining_time":0.8080583031},
{"learn":[3.793565328],"iteration":514,"passed_time":0.855774955,"remaining_time":0.8059239867},
{"learn":[3.791600047],"iteration":515,"passed_time":0.8569068176,"remaining_time":0.8037653095},
{"learn":[3.790221608],"iteration":516,"passed_time":0.8579665881,"remaining_time":0.8015432535},
{"learn":[3.787284267],"iteration":517,"passed_time":0.8590895082,"remaining_time":0.7993844459},
{"learn":[3.784784868],"iteration":518,"passed_time":0.8626625361,"remaining_time":0.7995003466},
{"learn":[3.782578414],"iteration":519,"passed_time":0.863865293,"remaining_time":0.7974141166},
{"learn":[3.782482986],"iteration":520,"passed_time":0.8649752863,"remaining_time":0.7952459926},
{"learn":[3.778915509],"iteration":521,"passed_time":0.8659893496,"remaining_time":0.7929940788},
{"learn":[3.778282435],"iteration":522,"passed_time":0.8670361874,"remaining_time":0.7907767904},
{"learn":[3.776404921],"iteration":523,"passed_time":0.8681705719,"remaining_time":0.7886434966},
{"learn":[3.77496784],"iteration":524,"passed_time":0.869323063,"remaining_time":0.7865303904},
{"learn":[3.773630962],"iteration":525,"passed_time":0.8706410714,"remaining_time":0.7845700909},
{"learn":[3.771935276],"iteration":526,"passed_time":0.8717040269,"remaining_time":0.7823833107},
{"learn":[3.768641453],"iteration":527,"passed_time":0.8738195919,"remaining_time":0.7811417564},
{"learn":[3.765258715],"iteration":528,"passed_time":0.8768216875,"remaining_time":0.7806862284},
{"learn":[3.761872551],"iteration":529,"passed_time":0.8786134135,"remaining_time":0.7791477441},
{"learn":[3.761155685],"iteration":530,"passed_time":0.8798996908,"remaining_time":0.7771618738},
{"learn":[3.759655352],"iteration":531,"passed_time":0.8813970775,"remaining_time":0.7753643464},
{"learn":[3.756430867],"iteration":532,"passed_time":0.882800758,"remaining_time":0.7734858423},
{"learn":[3.75545942],"iteration":533,"passed_time":0.8844261357,"remaining_time":0.7718025828},
{"learn":[3.752216963],"iteration":534,"passed_time":0.8859227509,"remaining_time":0.7700076246},
{"learn":[3.751748103],"iteration":535,"passed_time":0.891470912,"remaining_time":0.771721088},
{"learn":[3.751389201],"iteration":536,"passed_time":0.8933245679,"remaining_time":0.7702221135},
{"learn":[3.7492567],"iteration":537,"passed_time":0.8947310271,"remaining_time":0.7683377965},
{"learn":[3.744606052],"iteration":538,"passed_time":0.8967028443,"remaining_time":0.7669387963},
{"learn":[3.743429706],"iteration":539,"passed_time":0.8981282462,"remaining_time":0.7650722098},
{"learn":[3.741006417],"iteration":540,"passed_time":0.8993596338,"remaining_time":0.7630426468},
{"learn":[3.735982497],"iteration":541,"passed_time":0.9007950881,"remaining_time":0.7611884692},
{"learn":[3.734410427],"iteration":542,"passed_time":0.9030708058,"remaining_time":0.760043017},
{"learn":[3.73258186],"iteration":543,"passed_time":0.9046779737,"remaining_time":0.7583330073},
{"learn":[3.73047021],"iteration":544,"passed_time":0.9058005051,"remaining_time":0.7562187703},
{"learn":[3.729831601],"iteration":545,"passed_time":0.9071909708,"remaining_time":0.7543309538},
{"learn":[3.72783827],"iteration":546,"passed_time":0.908400024,"remaining_time":0.7522947182},
{"learn":[3.725692346],"iteration":547,"passed_time":0.9098246654,"remaining_time":0.7504393225},
{"learn":[3.724426329],"iteration":548,"passed_time":0.9113713011,"remaining_time":0.7486857137},
{"learn":[3.723747838],"iteration":549,"passed_time":0.9127400587,"remaining_time":0.7467873208},
{"learn":[3.722069556],"iteration":550,"passed_time":0.9140668047,"remaining_time":0.7448566158},
{"learn":[3.720248716],"iteration":551,"passed_time":0.9176277612,"remaining_time":0.7447413714},
{"learn":[3.717759548],"iteration":552,"passed_time":0.9191770222,"remaining_time":0.7429875749},
{"learn":[3.717204904],"iteration":553,"passed_time":0.9205098159,"remaining_time":0.7410602489},
{"learn":[3.712622182],"iteration":554,"passed_time":0.921690978,"remaining_time":0.7390134869},
{"learn":[3.711349676],"iteration":555,"passed_time":0.9227696023,"remaining_time":0.7368879558},
{"learn":[3.709754108],"iteration":556,"passed_time":0.9240015296,"remaining_time":0.7348881106},
{"learn":[3.709114276],"iteration":557,"passed_time":0.9253533526,"remaining_time":0.732985989},
{"learn":[3.707664366],"iteration":558,"passed_time":0.9266425195,"remaining_time":0.7310364063},
{"learn":[3.7053499],"iteration":559,"passed_time":0.9279136537,"remaining_time":0.7290750136},
{"learn":[3.702454065],"iteration":560,"passed_time":0.9300980955,"remaining_time":0.7278307735},
{"learn":[3.700823494],"iteration":561,"passed_time":0.9321668318,"remaining_time":0.7264930112},
{"learn":[3.698965408],"iteration":562,"passed_time":0.9335147393,"remaining_time":0.7245931458},
{"learn":[3.69693668],"iteration":563,"passed_time":0.9346010316,"remaining_time":0.722492996},
{"learn":[3.694910295],"iteration":564,"passed_time":0.9357825824,"remaining_time":0.7204697758},
{"learn":[3.692667251],"iteration":565,"passed_time":0.9370796952,"remaining_time":0.7185381409},
{"learn":[3.690951158],"iteration":566,"passed_time":0.9381043867,"remaining_time":0.7164007045},
{"learn":[3.688534463],"iteration":567,"passed_time":0.9393147781,"remaining_time":0.7144084228},
{"learn":[3.685636834],"iteration":568,"passed_time":0.9405383515,"remaining_time":0.7124288743},
{"learn":[3.682325276],"iteration":569,"passed_time":0.9416888874,"remaining_time":0.7103968799},
{"learn":[3.680629231],"iteration":570,"passed_time":0.9432152221,"remaining_time":0.7086503157},
{"learn":[3.678984996],"iteration":571,"passed_time":0.9451538156,"remaining_time":0.7072129949},
{"learn":[3.676706177],"iteration":572,"passed_time":0.9465052767,"remaining_time":0.705336393},
{"learn":[3.674023683],"iteration":573,"passed_time":0.947491501,"remaining_time":0.7031905565},
{"learn":[3.671916682],"iteration":574,"passed_time":0.9484949688,"remaining_time":0.7010614986},
{"learn":[3.669739118],"iteration":575,"passed_time":0.9494815028,"remaining_time":0.698923884},
{"learn":[3.666342997],"iteration":576,"passed_time":0.9504583262,"remaining_time":0.6967831403},
{"learn":[3.664971803],"iteration":577,"passed_time":0.9514800374,"remaining_time":0.6946791968},
{"learn":[3.664870231],"iteration":578,"passed_time":0.9525181123,"remaining_time":0.69259089},
{"learn":[3.657995407],"iteration":579,"passed_time":0.9536631049,"remaining_time":0.6905836277},
{"learn":[3.656149037],"iteration":580,"passed_time":0.9546694858,"remaining_time":0.688479371},
{"learn":[3.654265846],"iteration":581,"passed_time":0.9556942059,"remaining_time":0.6863920585},
{"learn":[3.653691866],"iteration":582,"passed_time":0.9572151073,"remaining_time":0.6846632928},
{"learn":[3.65153498],"iteration":583,"passed_time":0.959476309,"remaining_time":0.6834625763},
{"learn":[3.649616574],"iteration":584,"passed_time":0.9609793859,"remaining_time":0.681720419},
{"learn":[3.646897879],"iteration":585,"passed_time":0.9622991404,"remaining_time":0.6798495633},
{"learn":[3.644774255],"iteration":586,"passed_time":0.9638281968,"remaining_time":0.6781278454},
{"learn":[3.642242478],"iteration":587,"passed_time":0.9650242711,"remaining_time":0.6761734689},
{"learn":[3.638038515],"iteration":588,"passed_time":0.966154239,"remaining_time":0.6741755386},
{"learn":[3.636399526],"iteration":589,"passed_time":0.9673816086,"remaining_time":0.6722482365},
{"learn":[3.634056348],"iteration":590,"passed_time":0.9687756481,"remaining_time":0.6704386465},
{"learn":[3.632670812],"iteration":591,"passed_time":0.9699858456,"remaining_time":0.6685037584},
{"learn":[3.63068599],"iteration":592,"passed_time":0.9721770136,"remaining_time":0.6672445945},
{"learn":[3.629575358],"iteration":593,"passed_time":0.9745482526,"remaining_time":0.6661053713},
{"learn":[3.627679892],"iteration":594,"passed_time":0.9756769502,"remaining_time":0.6641162434},
{"learn":[3.62473819],"iteration":595,"passed_time":0.9769339211,"remaining_time":0.6622169532},
{"learn":[3.623445238],"iteration":596,"passed_time":0.9783532525,"remaining_time":0.660429415},
{"learn":[3.619962605],"iteration":597,"passed_time":0.979510418,"remaining_time":0.6584668696},
{"learn":[3.618166525],"iteration":598,"passed_time":0.9807118149,"remaining_time":0.656536624},
{"learn":[3.616579314],"iteration":599,"passed_time":0.981845427,"remaining_time":0.654563618},
{"learn":[3.614470807],"iteration":600,"passed_time":0.9830102002,"remaining_time":0.652614093},
{"learn":[3.612480378],"iteration":601,"passed_time":0.9845489404,"remaining_time":0.6509144157},
{"learn":[3.611459495],"iteration":602,"passed_time":0.9866019727,"remaining_time":0.6495538693},
{"learn":[3.609075171],"iteration":603,"passed_time":0.987912145,"remaining_time":0.6477039891},
{"learn":[3.607959495],"iteration":604,"passed_time":0.9890855165,"remaining_time":0.6457665769},
{"learn":[3.605502861],"iteration":605,"passed_time":0.9904908583,"remaining_time":0.6439825052},
{"learn":[3.602598914],"iteration":606,"passed_time":0.9919094216,"remaining_time":0.6422082416},
{"learn":[3.599671069],"iteration":607,"passed_time":0.9932106917,"remaining_time":0.6403595249},
{"learn":[3.598357878],"iteration":608,"passed_time":0.9945301809,"remaining_time":0.6385243034},
{"learn":[3.597827692],"iteration":609,"passed_time":0.9957799202,"remaining_time":0.6366461785},
{"learn":[3.596962084],"iteration":610,"passed_time":0.9969912778,"remaining_time":0.6347456744},
{"learn":[3.595404898],"iteration":611,"passed_time":0.9990910911,"remaining_time":0.6334106917},
{"learn":[3.593066682],"iteration":612,"passed_time":1.001041804,"remaining_time":0.6319790833},
{"learn":[3.58765348],"iteration":613,"passed_time":1.002320723,"remaining_time":0.6301234511},
{"learn":[3.584542549],"iteration":614,"passed_time":1.003651194,"remaining_time":0.6283019667},
{"learn":[3.58366855],"iteration":615,"passed_time":1.004884574,"remaining_time":0.6264215527},
{"learn":[3.582071131],"iteration":616,"passed_time":1.006135422,"remaining_time":0.6245540791},
{"learn":[3.58197282],"iteration":617,"passed_time":1.007530486,"remaining_time":0.6227777438},
{"learn":[3.577993389],"iteration":618,"passed_time":1.008818279,"remaining_time":0.6209366142},
{"learn":[3.576491367],"iteration":619,"passed_time":1.010447112,"remaining_time":0.6193062944},
{"learn":[3.575689302],"iteration":620,"passed_time":1.012451285,"remaining_time":0.6179050518},
{"learn":[3.57276988],"iteration":621,"passed_time":1.014315942,"remaining_time":0.6164170834},
{"learn":[3.570697119],"iteration":622,"passed_time":1.015564995,"remaining_time":0.6145553822},
{"learn":[3.566669624],"iteration":623,"passed_time":1.016918204,"remaining_time":0.6127584049},
{"learn":[3.565316359],"iteration":624,"passed_time":1.018296761,"remaining_time":0.6109780567},
{"learn":[3.563702213],"iteration":625,"passed_time":1.019497904,"remaining_time":0.6090929967},
{"learn":[3.560950897],"iteration":626,"passed_time":1.020804313,"remaining_time":0.6072727414},
{"learn":[3.559543203],"iteration":627,"passed_time":1.022094567,"remaining_time":0.6054445521},
{"learn":[3.557912097],"iteration":628,"passed_time":1.02351785,"remaining_time":0.6036965381},
{"learn":[3.555167312],"iteration":629,"passed_time":1.025349101,"remaining_time":0.6021891548},
{"learn":[3.553154913],"iteration":630,"passed_time":1.027180444,"remaining_time":0.6006807985},
{"learn":[3.55268488],"iteration":631,"passed_time":1.02850112,"remaining_time":0.59887407},
{"learn":[3.552178299],"iteration":632,"passed_time":1.029744459,"remaining_time":0.5970240387},
{"learn":[3.549665508],"iteration":633,"passed_time":1.030998201,"remaining_time":0.5951819269},
{"learn":[3.548261527],"iteration":634,"passed_time":1.032370285,"remaining_time":0.5934096913},
{"learn":[3.546957285],"iteration":635,"passed_time":1.033699047,"remaining_time":0.5916139202},
{"learn":[3.545312773],"iteration":636,"passed_time":1.034958832,"remaining_time":0.5897803079},
{"learn":[3.544543814],"iteration":637,"passed_time":1.037550834,"remaining_time":0.5887043918},
{"learn":[3.541984205],"iteration":638,"passed_time":1.042367149,"remaining_time":0.5888803454},
{"learn":[3.541249703],"iteration":639,"passed_time":1.045396752,"remaining_time":0.5880356729},
{"learn":[3.534762375],"iteration":640,"passed_time":1.047395557,"remaining_time":0.5866068719},
{"learn":[3.53193958],"iteration":641,"passed_time":1.04908693,"remaining_time":0.5850048613},
{"learn":[3.531686047],"iteration":642,"passed_time":1.051289038,"remaining_time":0.5836861376},
{"learn":[3.530051833],"iteration":643,"passed_time":1.054847519,"remaining_time":0.5831144668},
{"learn":[3.528174058],"iteration":644,"passed_time":1.056127696,"remaining_time":0.5812795846},
{"learn":[3.527856626],"iteration":645,"passed_time":1.057460046,"remaining_time":0.5794750096},
{"learn":[3.526617805],"iteration":646,"passed_time":1.058743691,"remaining_time":0.5776453214},
{"learn":[3.525672809],"iteration":647,"passed_time":1.060511615,"remaining_time":0.5760803832},
{"learn":[3.521116664],"iteration":648,"passed_time":1.062942781,"remaining_time":0.5748735226},
{"learn":[3.518838528],"iteration":649,"passed_time":1.077110085,"remaining_time":0.5799823535},
{"learn":[3.517731994],"iteration":650,"passed_time":1.079092971,"remaining_time":0.5784999185},
{"learn":[3.514992407],"iteration":651,"passed_time":1.080818852,"remaining_time":0.5768787737},
{"learn":[3.51442972],"iteration":652,"passed_time":1.084258244,"remaining_time":0.576167857},
{"learn":[3.513981449],"iteration":653,"passed_time":1.085665649,"remaining_time":0.5743735697},
{"learn":[3.512608238],"iteration":654,"passed_time":1.086800766,"remaining_time":0.5724370445},
{"learn":[3.512483881],"iteration":655,"passed_time":1.087694961,"remaining_time":0.5703766259},
{"learn":[3.512284402],"iteration":656,"passed_time":1.088979995,"remaining_time":0.5685238026},
{"learn":[3.510144437],"iteration":657,"passed_time":1.090504689,"remaining_time":0.5667972697},
{"learn":[3.509316425],"iteration":658,"passed_time":1.091878063,"remaining_time":0.5649930491},
{"learn":[3.505804641],"iteration":659,"passed_time":1.093020517,"remaining_time":0.5630711752},
{"learn":[3.504436606],"iteration":660,"passed_time":1.094392694,"remaining_time":0.5612694756},
{"learn":[3.502605224],"iteration":661,"passed_time":1.096365709,"remaining_time":0.5597758452},
{"learn":[3.50109123],"iteration":662,"passed_time":1.098083465,"remaining_time":0.5581510223},
{"learn":[3.499949232],"iteration":663,"passed_time":1.099441376,"remaining_time":0.556343829},
{"learn":[3.499483526],"iteration":664,"passed_time":1.100757856,"remaining_time":0.5545171154},
{"learn":[3.499389977],"iteration":665,"passed_time":1.102004079,"remaining_time":0.5526567005},
{"learn":[3.496133273],"iteration":666,"passed_time":1.103188798,"remaining_time":0.5507674207},
{"learn":[3.495364005],"iteration":667,"passed_time":1.104535858,"remaining_time":0.5489609355},
{"learn":[3.492568694],"iteration":668,"passed_time":1.106279661,"remaining_time":0.5473521195},
{"learn":[3.491913978],"iteration":669,"passed_time":1.110429492,"remaining_time":0.5469279585},
{"learn":[3.490775334],"iteration":670,"passed_time":1.111826442,"remaining_time":0.5451429199},
{"learn":[3.489703783],"iteration":671,"passed_time":1.112976686,"remaining_time":0.5432386206},
{"learn":[3.486119727],"iteration":672,"passed_time":1.114293253,"remaining_time":0.5414173756},
{"learn":[3.485274898],"iteration":673,"passed_time":1.115750696,"remaining_time":0.5396657668},
{"learn":[3.484532049],"iteration":674,"passed_time":1.117248245,"remaining_time":0.5379343403},
{"learn":[3.483287656],"iteration":675,"passed_time":1.118756654,"remaining_time":0.5362088105},
{"learn":[3.483013432],"iteration":676,"passed_time":1.120763607,"remaining_time":0.5347217801},
{"learn":[3.480395591],"iteration":677,"passed_time":1.122942534,"remaining_time":0.5333148909},
{"learn":[3.479223655],"iteration":678,"passed_time":1.124714287,"remaining_time":0.5317132342},
{"learn":[3.476199552],"iteration":679,"passed_time":1.126353349,"remaining_time":0.530048635},
{"learn":[3.474425891],"iteration":680,"passed_time":1.127509413,"remaining_time":0.5281578603},
{"learn":[3.473365898],"iteration":681,"passed_time":1.128953991,"remaining_time":0.5264037673},
{"learn":[3.473255601],"iteration":682,"passed_time":1.130300706,"remaining_time":0.5246051593},
{"learn":[3.470150907],"iteration":683,"passed_time":1.131564751,"remaining_time":0.5227696805},
{"learn":[3.469978388],"iteration":684,"passed_time":1.132915648,"remaining_time":0.5209758087},
{"learn":[3.469814235],"iteration":685,"passed_time":1.134207126,"remaining_time":0.5191560313},
{"learn":[3.466765686],"iteration":686,"passed_time":1.136935794,"remaining_time":0.5179925816},
{"learn":[3.465370361],"iteration":687,"passed_time":1.138183502,"remaining_time":0.5161529833},
{"learn":[3.463098058],"iteration":688,"passed_time":1.139487692,"remaining_time":0.5143405985},
{"learn":[3.462452272],"iteration":689,"passed_time":1.140663972,"remaining_time":0.5124722193},
{"learn":[3.460940275],"iteration":690,"passed_time":1.141859969,"remaining_time":0.5106146606},
{"learn":[3.457327186],"iteration":691,"passed_time":1.143046402,"remaining_time":0.5087547568},
{"learn":[3.456935165],"iteration":692,"passed_time":1.144359535,"remaining_time":0.5069529253},
{"learn":[3.456513258],"iteration":693,"passed_time":1.14559408,"remaining_time":0.5051178508},
{"learn":[3.453775384],"iteration":694,"passed_time":1.146924466,"remaining_time":0.5033265642},
{"learn":[3.452722912],"iteration":695,"passed_time":1.149464528,"remaining_time":0.5020649663},
{"learn":[3.450490671],"iteration":696,"passed_time":1.151435285,"remaining_time":0.5005522114},
{"learn":[3.448773425],"iteration":697,"passed_time":1.152733934,"remaining_time":0.4987473469},
{"learn":[3.445139173],"iteration":698,"passed_time":1.153914201,"remaining_time":0.4968929537},
{"learn":[3.441722304],"iteration":699,"passed_time":1.155293095,"remaining_time":0.4951256122},
{"learn":[3.440614504],"iteration":700,"passed_time":1.156535682,"remaining_time":0.4933012395},
{"learn":[3.439888769],"iteration":701,"passed_time":1.157827235,"remaining_time":0.4914993108},
{"learn":[3.438654733],"iteration":702,"passed_time":1.158877376,"remaining_time":0.489596843},
{"learn":[3.437834959],"iteration":703,"passed_time":1.160056033,"remaining_time":0.487750832},
{"learn":[3.437334386],"iteration":704,"passed_time":1.164298885,"remaining_time":0.4871888951},
{"learn":[3.435460516],"iteration":705,"passed_time":1.166279661,"remaining_time":0.4856745329},
{"learn":[3.433573322],"iteration":706,"passed_time":1.167841724,"remaining_time":0.4839853255},
{"learn":[3.430441871],"iteration":707,"passed_time":1.169485263,"remaining_time":0.4823300802},
{"learn":[3.427458048],"iteration":708,"passed_time":1.182601894,"remaining_time":0.4853838522},
{"learn":[3.425563871],"iteration":709,"passed_time":1.184066389,"remaining_time":0.4836327503},
{"learn":[3.42390564],"iteration":710,"passed_time":1.185785493,"remaining_time":0.4819859458},
{"learn":[3.42292019],"iteration":711,"passed_time":1.187277105,"remaining_time":0.480246919},
{"learn":[3.422345561],"iteration":712,"passed_time":1.18860774,"remaining_time":0.4784437887},
{"learn":[3.419425383],"iteration":713,"passed_time":1.18991665,"remaining_time":0.4766332802},
{"learn":[3.417317762],"iteration":714,"passed_time":1.191751699,"remaining_time":0.4750338939},
{"learn":[3.415697119],"iteration":715,"passed_time":1.194468715,"remaining_time":0.4737836801},
{"learn":[3.414284185],"iteration":716,"passed_time":1.196141233,"remaining_time":0.4721171114},
{"learn":[3.411763738],"iteration":717,"passed_time":1.19739018,"remaining_time":0.4702841655},
{"learn":[3.411001885],"iteration":718,"passed_time":1.198619521,"remaining_time":0.4684451814},
{"learn":[3.407796868],"iteration":719,"passed_time":1.199728863,"remaining_time":0.4665612245},
{"learn":[3.405859051],"iteration":720,"passed_time":1.200742469,"remaining_time":0.46464237},
{"learn":[3.404151194],"iteration":721,"passed_time":1.202085479,"remaining_time":0.4628528577},
{"learn":[3.402803939],"iteration":722,"passed_time":1.20325359,"remaining_time":0.4609975717},
{"learn":[3.401044833],"iteration":723,"passed_time":1.204578609,"remaining_time":0.459204},
{"learn":[3.400688556],"iteration":724,"passed_time":1.206117173,"remaining_time":0.4574927206},
{"learn":[3.400499064],"iteration":725,"passed_time":1.208341185,"remaining_time":0.4560406124},
{"learn":[3.400422688],"iteration":726,"passed_time":1.209695339,"remaining_time":0.4542597353},
{"learn":[3.399957355],"iteration":727,"passed_time":1.210990837,"remaining_time":0.4524581148},
{"learn":[3.398286793],"iteration":728,"passed_time":1.212254163,"remaining_time":0.4506459233},
{"learn":[3.396201876],"iteration":729,"passed_time":1.213678301,"remaining_time":0.4488947141},
{"learn":[3.393550924],"iteration":730,"passed_time":1.214852735,"remaining_time":0.4470525114},
{"learn":[3.390136884],"iteration":731,"passed_time":1.216052168,"remaining_time":0.4452212855},
{"learn":[3.387239341],"iteration":732,"passed_time":1.217208982,"remaining_time":0.4433762596},
{"learn":[3.386723404],"iteration":733,"passed_time":1.220370769,"remaining_time":0.4422597065},
{"learn":[3.385420178],"iteration":734,"passed_time":1.222359978,"remaining_time":0.4407148221},
{"learn":[3.381874931],"iteration":735,"passed_time":1.223446096,"remaining_time":0.4388447953},
{"learn":[3.380780961],"iteration":736,"passed_time":1.224593879,"remaining_time":0.4369989012},
{"learn":[3.379451173],"iteration":737,"passed_time":1.225675923,"remaining_time":0.4351315606},
{"learn":[3.376742777],"iteration":738,"passed_time":1.226710068,"remaining_time":0.4332494286},
{"learn":[3.374570813],"iteration":739,"passed_time":1.227808677,"remaining_time":0.431392238},
{"learn":[3.373494694],"iteration":740,"passed_time":1.228808685,"remaining_time":0.4295026307},
{"learn":[3.3714259],"iteration":741,"passed_time":1.230063461,"remaining_time":0.4277040067},
{"learn":[3.369672511],"iteration":742,"passed_time":1.231365237,"remaining_time":0.4259231034},
{"learn":[3.368351482],"iteration":743,"passed_time":1.23398754,"remaining_time":0.4245978632},
{"learn":[3.367315822],"iteration":744,"passed_time":1.235253681,"remaining_time":0.4228049511},
{"learn":[3.363642241],"iteration":745,"passed_time":1.236309342,"remaining_time":0.4209417866},
{"learn":[3.360859628],"iteration":746,"passed_time":1.237645183,"remaining_time":0.4191756777},
{"learn":[3.359446087],"iteration":747,"passed_time":1.238826019,"remaining_time":0.4173584985},
{"learn":[3.359072191],"iteration":748,"passed_time":1.24010402,"remaining_time":0.4155755794},
{"learn":[3.357704533],"iteration":749,"passed_time":1.241396565,"remaining_time":0.413798855},
{"learn":[3.356660328],"iteration":750,"passed_time":1.242448877,"remaining_time":0.4119437689},
{"learn":[3.355224064],"iteration":751,"passed_time":1.243345751,"remaining_time":0.410039556},
{"learn":[3.354824563],"iteration":752,"passed_time":1.244931042,"remaining_time":0.4083638346},
{"learn":[3.353518996],"iteration":753,"passed_time":1.247038909,"remaining_time":0.4068588483},
{"learn":[3.352115597],"iteration":754,"passed_time":1.24930106,"remaining_time":0.4054023308},
{"learn":[3.348115311],"iteration":755,"passed_time":1.251101998,"remaining_time":0.4037948249},
{"learn":[3.348031043],"iteration":756,"passed_time":1.252349159,"remaining_time":0.402009043},
{"learn":[3.34659284],"iteration":757,"passed_time":1.253730384,"remaining_time":0.400267484},
{"learn":[3.344540897],"iteration":758,"passed_time":1.254820822,"remaining_time":0.3984345431},
{"learn":[3.34335553],"iteration":759,"passed_time":1.255869889,"remaining_time":0.3965904913},
{"learn":[3.34227938],"iteration":760,"passed_time":1.256992477,"remaining_time":0.3947716189},
{"learn":[3.340277565],"iteration":761,"passed_time":1.257970271,"remaining_time":0.3929093496},
{"learn":[3.338750174],"iteration":762,"passed_time":1.259649275,"remaining_time":0.3912672059},
{"learn":[3.336890692],"iteration":763,"passed_time":1.261792542,"remaining_time":0.3897683768},
{"learn":[3.333626439],"iteration":764,"passed_time":1.262930853,"remaining_time":0.3879591509},
{"learn":[3.333480502],"iteration":765,"passed_time":1.264117703,"remaining_time":0.3861665047},
{"learn":[3.332022739],"iteration":766,"passed_time":1.265197997,"remaining_time":0.3843430683},
{"learn":[3.330144933],"iteration":767,"passed_time":1.266226438,"remaining_time":0.3825059032},
{"learn":[3.328286434],"iteration":768,"passed_time":1.267449993,"remaining_time":0.3807294518},
{"learn":[3.325107099],"iteration":769,"passed_time":1.268742,"remaining_time":0.3789748831},
{"learn":[3.324665163],"iteration":770,"passed_time":1.269855218,"remaining_time":0.3771684111},
{"learn":[3.324600322],"iteration":771,"passed_time":1.271019984,"remaining_time":0.3753789589},
{"learn":[3.318570138],"iteration":772,"passed_time":1.271873705,"remaining_time":0.3734997815},
{"learn":[3.316304778],"iteration":773,"passed_time":1.273339596,"remaining_time":0.3718020009},
{"learn":[3.313794673],"iteration":774,"passed_time":1.275153855,"remaining_time":0.370205958},
{"learn":[3.312451701],"iteration":775,"passed_time":1.276315072,"remaining_time":0.3684208454},
{"learn":[3.310624939],"iteration":776,"passed_time":1.277436836,"remaining_time":0.3666260159},
{"learn":[3.307028721],"iteration":777,"passed_time":1.278620099,"remaining_time":0.3648504653},
{"learn":[3.304722992],"iteration":778,"passed_time":1.279725671,"remaining_time":0.3630543944},
{"learn":[3.301878014],"iteration":779,"passed_time":1.280759131,"remaining_time":0.3612397549},
{"learn":[3.30009992],"iteration":780,"passed_time":1.281993404,"remaining_time":0.3594834257},
{"learn":[3.299055697],"iteration":781,"passed_time":1.283067365,"remaining_time":0.3576837413},
{"learn":[3.298415591],"iteration":782,"passed_time":1.284048523,"remaining_time":0.355860191},
{"learn":[3.293359889],"iteration":783,"passed_time":1.285241687,"remaining_time":0.3540971995},
{"learn":[3.288302398],"iteration":784,"passed_time":1.286304155,"remaining_time":0.3522998641},
{"learn":[3.28369124],"iteration":785,"passed_time":1.288429097,"remaining_time":0.3507936728},
{"learn":[3.282372171],"iteration":786,"passed_time":1.289959908,"remaining_time":0.3491251086},
{"learn":[3.281990019],"iteration":787,"passed_time":1.291009555,"remaining_time":0.3473274437},
{"learn":[3.279807891],"iteration":788,"passed_time":1.292008996,"remaining_time":0.3455182485},
{"learn":[3.276831856],"iteration":789,"passed_time":1.293058533,"remaining_time":0.3437244202},
{"learn":[3.272876997],"iteration":790,"passed_time":1.294239009,"remaining_time":0.3419670705},
{"learn":[3.270498536],"iteration":791,"passed_time":1.295301269,"remaining_time":0.3401801313},
{"learn":[3.268984099],"iteration":792,"passed_time":1.296310527,"remaining_time":0.3383811842},
{"learn":[3.267840763],"iteration":793,"passed_time":1.297309423,"remaining_time":0.3365815379},
{"learn":[3.265674334],"iteration":794,"passed_time":1.298463449,"remaining_time":0.3348239083},
{"learn":[3.261490535],"iteration":795,"passed_time":1.299579857,"remaining_time":0.3330581542},
{"learn":[3.259106649],"iteration":796,"passed_time":1.300865052,"remaining_time":0.3313370207},
{"learn":[3.257317456],"iteration":797,"passed_time":1.302860677,"remaining_time":0.3297968131},
{"learn":[3.256227291],"iteration":798,"passed_time":1.304078977,"remaining_time":0.3280599179},
{"learn":[3.254990807],"iteration":799,"passed_time":1.305169451,"remaining_time":0.3262923627},
{"learn":[3.25299311],"iteration":800,"passed_time":1.306191789,"remaining_time":0.3245095706},
{"learn":[3.24980812],"iteration":801,"passed_time":1.307306538,"remaining_time":0.3227514896},
{"learn":[3.248835362],"iteration":802,"passed_time":1.308330923,"remaining_time":0.3209728416},
{"learn":[3.247796595],"iteration":803,"passed_time":1.30940146,"remaining_time":0.3192073211},
{"learn":[3.246845996],"iteration":804,"passed_time":1.31050242,"remaining_time":0.3174508968},
{"learn":[3.24462183],"iteration":805,"passed_time":1.311807877,"remaining_time":0.3157453202},
{"learn":[3.243195551],"iteration":806,"passed_time":1.312865612,"remaining_time":0.3139814909},
{"learn":[3.241856256],"iteration":807,"passed_time":1.314490939,"remaining_time":0.3123542825},
{"learn":[3.240226539],"iteration":808,"passed_time":1.31637824,"remaining_time":0.3107889293},
{"learn":[3.236801481],"iteration":809,"passed_time":1.317618363,"remaining_time":0.3090709739},
{"learn":[3.235722534],"iteration":810,"passed_time":1.318611543,"remaining_time":0.3072966481},
{"learn":[3.233101758],"iteration":811,"passed_time":1.319651449,"remaining_time":0.3055350645},
{"learn":[3.229180678],"iteration":812,"passed_time":1.321149606,"remaining_time":0.3038806598},
{"learn":[3.228227594],"iteration":813,"passed_time":1.322367648,"remaining_time":0.3021626321},
{"learn":[3.227356597],"iteration":814,"passed_time":1.323520322,"remaining_time":0.3004309934},
{"learn":[3.226505842],"iteration":815,"passed_time":1.324600661,"remaining_time":0.2986844627},
{"learn":[3.224579338],"iteration":816,"passed_time":1.3256522,"remaining_time":0.2969331121},
{"learn":[3.223317875],"iteration":817,"passed_time":1.326840286,"remaining_time":0.2952138534},
{"learn":[3.221618664],"iteration":818,"passed_time":1.328504454,"remaining_time":0.2936011063},
{"learn":[3.217201288],"iteration":819,"passed_time":1.331207635,"remaining_time":0.2922163102},
{"learn":[3.216582881],"iteration":820,"passed_time":1.332644996,"remaining_time":0.2905523195},
{"learn":[3.215719498],"iteration":821,"passed_time":1.333889968,"remaining_time":0.2888472193},
{"learn":[3.214502266],"iteration":822,"passed_time":1.335203062,"remaining_time":0.2871578881},
{"learn":[3.211896763],"iteration":823,"passed_time":1.336420517,"remaining_time":0.2854490424},
{"learn":[3.209852258],"iteration":824,"passed_time":1.337772602,"remaining_time":0.2837699458},
{"learn":[3.209535169],"iteration":825,"passed_time":1.339632837,"remaining_time":0.2821986847},
{"learn":[3.208846445],"iteration":826,"passed_time":1.341226038,"remaining_time":0.2805708642},
{"learn":[3.203293963],"iteration":827,"passed_time":1.343044757,"remaining_time":0.2789899737},
{"learn":[3.200832004],"iteration":828,"passed_time":1.344852217,"remaining_time":0.2774061872},
{"learn":[3.199784125],"iteration":829,"passed_time":1.345967022,"remaining_time":0.2756799925},
{"learn":[3.196495727],"iteration":830,"passed_time":1.347163438,"remaining_time":0.2739718665},
{"learn":[3.194703877],"iteration":831,"passed_time":1.348494398,"remaining_time":0.2722921381},
{"learn":[3.192141563],"iteration":832,"passed_time":1.349710954,"remaining_time":0.2705903114},
{"learn":[3.191524108],"iteration":833,"passed_time":1.350984296,"remaining_time":0.2689009511},
{"learn":[3.188472396],"iteration":834,"passed_time":1.352419136,"remaining_time":0.2672445},
{"learn":[3.18574932],"iteration":835,"passed_time":1.35380148,"remaining_time":0.2655782807},
{"learn":[3.182429026],"iteration":836,"passed_time":1.35635099,"remaining_time":0.2641400376},
{"learn":[3.181880908],"iteration":837,"passed_time":1.359038091,"remaining_time":0.2627257407},
{"learn":[3.179973851],"iteration":838,"passed_time":1.360308603,"remaining_time":0.2610365735},
{"learn":[3.179268791],"iteration":839,"passed_time":1.361602279,"remaining_time":0.2593528151},
{"learn":[3.177821038],"iteration":840,"passed_time":1.36267129,"remaining_time":0.257627509},
{"learn":[3.177593681],"iteration":841,"passed_time":1.363767253,"remaining_time":0.2559088194},
{"learn":[3.176172946],"iteration":842,"passed_time":1.365043482,"remaining_time":0.25422518},
{"learn":[3.174560979],"iteration":843,"passed_time":1.366131445,"remaining_time":0.2525077079},
{"learn":[3.173489092],"iteration":844,"passed_time":1.367428738,"remaining_time":0.2508301235},
{"learn":[3.171745195],"iteration":845,"passed_time":1.369508187,"remaining_time":0.2492958165},
{"learn":[3.171696824],"iteration":846,"passed_time":1.371825984,"remaining_time":0.247803277},
{"learn":[3.171536569],"iteration":847,"passed_time":1.37316438,"remaining_time":0.2461332379},
{"learn":[3.171357849],"iteration":848,"passed_time":1.374459155,"remaining_time":0.2444562219},
{"learn":[3.169697829],"iteration":849,"passed_time":1.375616853,"remaining_time":0.2427559152},
{"learn":[3.166278261],"iteration":850,"passed_time":1.37687824,"remaining_time":0.2410750385},
{"learn":[3.16559106],"iteration":851,"passed_time":1.37801442,"remaining_time":0.2393733968},
{"learn":[3.165156205],"iteration":852,"passed_time":1.379042556,"remaining_time":0.2376544617},
{"learn":[3.16340211],"iteration":853,"passed_time":1.380177901,"remaining_time":0.2359554726},
{"learn":[3.162805902],"iteration":854,"passed_time":1.381285747,"remaining_time":0.2342531384},
{"learn":[3.161255128],"iteration":855,"passed_time":1.383870888,"remaining_time":0.2328007101},
{"learn":[3.159235277],"iteration":856,"passed_time":1.385685454,"remaining_time":0.2312170595},
{"learn":[3.158113177],"iteration":857,"passed_time":1.38698088,"remaining_time":0.2295469522},
{"learn":[3.157412761],"iteration":858,"passed_time":1.388087325,"remaining_time":0.2278466971},
{"learn":[3.155118549],"iteration":859,"passed_time":1.389139782,"remaining_time":0.2261390343},
{"learn":[3.154324442],"iteration":860,"passed_time":1.390264663,"remaining_time":0.2244445855},
{"learn":[3.151644979],"iteration":861,"passed_time":1.391336713,"remaining_time":0.2227430004},
{"learn":[3.150182621],"iteration":862,"passed_time":1.392446171,"remaining_time":0.2210488128},
{"learn":[3.149159769],"iteration":863,"passed_time":1.393587192,"remaining_time":0.2193609469},
{"learn":[3.148356084],"iteration":864,"passed_time":1.394678097,"remaining_time":0.2176665238},
{"learn":[3.14520552],"iteration":865,"passed_time":1.395746006,"remaining_time":0.2159699363},
{"learn":[3.143648705],"iteration":866,"passed_time":1.397714061,"remaining_time":0.2144128837},
{"learn":[3.141804136],"iteration":867,"passed_time":1.401248547,"remaining_time":0.2130930971},
{"learn":[3.141738212],"iteration":868,"passed_time":1.403195669,"remaining_time":0.2115289214},
{"learn":[3.140568904],"iteration":869,"passed_time":1.40471654,"remaining_time":0.2099001726},
{"learn":[3.138929611],"iteration":870,"passed_time":1.40626257,"remaining_time":0.2082753979},
{"learn":[3.136450239],"iteration":871,"passed_time":1.40776483,"remaining_time":0.2066443788},
{"learn":[3.135724757],"iteration":872,"passed_time":1.409144024,"remaining_time":0.2049957515},
{"learn":[3.132929271],"iteration":873,"passed_time":1.41168027,"remaining_time":0.2035145469},
{"learn":[3.13272866],"iteration":874,"passed_time":1.41488589,"remaining_time":0.2021265557},
{"learn":[3.132161843],"iteration":875,"passed_time":1.416191466,"remaining_time":0.2004654586},
{"learn":[3.13153038],"iteration":876,"passed_time":1.417449383,"remaining_time":0.1987984882},
{"learn":[3.128814566],"iteration":877,"passed_time":1.418609523,"remaining_time":0.1971188631},
{"learn":[3.128188124],"iteration":878,"passed_time":1.419671826,"remaining_time":0.1954269521},
{"learn":[3.128038175],"iteration":879,"passed_time":1.420733832,"remaining_time":0.1937364316},
{"learn":[3.127036037],"iteration":880,"passed_time":1.421774441,"remaining_time":0.1920444478},
{"learn":[3.124685562],"iteration":881,"passed_time":1.422942572,"remaining_time":0.1903710016},
{"learn":[3.123455614],"iteration":882,"passed_time":1.424398131,"remaining_time":0.1887367851},
{"learn":[3.122892165],"iteration":883,"passed_time":1.426897154,"remaining_time":0.187239898},
{"learn":[3.121255606],"iteration":884,"passed_time":1.428249675,"remaining_time":0.1855917656},
{"learn":[3.121102901],"iteration":885,"passed_time":1.429412521,"remaining_time":0.1839198955},
{"learn":[3.12037989],"iteration":886,"passed_time":1.430641181,"remaining_time":0.1822575575},
{"learn":[3.118514329],"iteration":887,"passed_time":1.431714955,"remaining_time":0.1805766609},
{"learn":[3.116920397],"iteration":888,"passed_time":1.432870774,"remaining_time":0.1789073744},
{"learn":[3.11530305],"iteration":889,"passed_time":1.433963031,"remaining_time":0.1772313858},
{"learn":[3.115046054],"iteration":890,"passed_time":1.435090773,"remaining_time":0.1755610485},
{"learn":[3.114766142],"iteration":891,"passed_time":1.436121369,"remaining_time":0.1738801657},
{"learn":[3.113365125],"iteration":892,"passed_time":1.43735299,"remaining_time":0.1722248263},
{"learn":[3.110723536],"iteration":893,"passed_time":1.439111526,"remaining_time":0.1706329103},
{"learn":[3.109670743],"iteration":894,"passed_time":1.441184405,"remaining_time":0.1690775},
{"learn":[3.108394251],"iteration":895,"passed_time":1.442590204,"remaining_time":0.1674435058},
{"learn":[3.106462891],"iteration":896,"passed_time":1.443631667,"remaining_time":0.1657681848},
{"learn":[3.106106245],"iteration":897,"passed_time":1.444678082,"remaining_time":0.1640948378},
{"learn":[3.105488969],"iteration":898,"passed_time":1.445689251,"remaining_time":0.1624189258},
{"learn":[3.10462787],"iteration":899,"passed_time":1.446760811,"remaining_time":0.1607512012},
{"learn":[3.101348363],"iteration":900,"passed_time":1.44776199,"remaining_time":0.1590770666},
{"learn":[3.099976914],"iteration":901,"passed_time":1.448877882,"remaining_time":0.1574168874},
{"learn":[3.09662452],"iteration":902,"passed_time":1.450108157,"remaining_time":0.1557702007},
{"learn":[3.094919903],"iteration":903,"passed_time":1.451260314,"remaining_time":0.1541161395},
{"learn":[3.093927041],"iteration":904,"passed_time":1.453094603,"remaining_time":0.1525347926},
{"learn":[3.092093227],"iteration":905,"passed_time":1.454990009,"remaining_time":0.1509592283},
{"learn":[3.090247722],"iteration":906,"passed_time":1.456314027,"remaining_time":0.149324371},
{"learn":[3.087941802],"iteration":907,"passed_time":1.457541079,"remaining_time":0.1476803737},
{"learn":[3.085140146],"iteration":908,"passed_time":1.458644935,"remaining_time":0.1460249605},
{"learn":[3.0840741],"iteration":909,"passed_time":1.459745038,"remaining_time":0.1443703884},
{"learn":[3.083273376],"iteration":910,"passed_time":1.460839354,"remaining_time":0.1427164681},
{"learn":[3.08246802],"iteration":911,"passed_time":1.462034844,"remaining_time":0.1410735375},
{"learn":[3.081933691],"iteration":912,"passed_time":1.46322423,"remaining_time":0.1394310054},
{"learn":[3.080442976],"iteration":913,"passed_time":1.464520847,"remaining_time":0.1377995545},
{"learn":[3.078409419],"iteration":914,"passed_time":1.465872754,"remaining_time":0.1361739717},
{"learn":[3.077820016],"iteration":915,"passed_time":1.469720603,"remaining_time":0.1347778719},
{"learn":[3.076508896],"iteration":916,"passed_time":1.471245881,"remaining_time":0.133166203},
{"learn":[3.075490856],"iteration":917,"passed_time":1.472369277,"remaining_time":0.1315188243},
{"learn":[3.073900169],"iteration":918,"passed_time":1.473786256,"remaining_time":0.1298984621},
{"learn":[3.072574426],"iteration":919,"passed_time":1.475064416,"remaining_time":0.1282664709},
{"learn":[3.071182361],"iteration":920,"passed_time":1.476715167,"remaining_time":0.1266672076},
{"learn":[3.070892559],"iteration":921,"passed_time":1.477901674,"remaining_time":0.1250285581},
{"learn":[3.070635502],"iteration":922,"passed_time":1.479150818,"remaining_time":0.1233961138},
{"learn":[3.067970909],"iteration":923,"passed_time":1.481039028,"remaining_time":0.1218170629},
{"learn":[3.066433883],"iteration":924,"passed_time":1.483016516,"remaining_time":0.1202445824},
{"learn":[3.066410891],"iteration":925,"passed_time":1.483830097,"remaining_time":0.1185782151},
{"learn":[3.064427641],"iteration":926,"passed_time":1.48498831,"remaining_time":0.116940827},
{"learn":[3.062930839],"iteration":927,"passed_time":1.486071518,"remaining_time":0.1152986523},
{"learn":[3.061021869],"iteration":928,"passed_time":1.487130489,"remaining_time":0.1136558285},
{"learn":[3.056745938],"iteration":929,"passed_time":1.488358615,"remaining_time":0.1120269926},
{"learn":[3.056449229],"iteration":930,"passed_time":1.48984453,"remaining_time":0.1104181231},
{"learn":[3.054962579],"iteration":931,"passed_time":1.491501116,"remaining_time":0.1088219698},
{"learn":[3.053047624],"iteration":932,"passed_time":1.492726159,"remaining_time":0.1071946974},
{"learn":[3.052330513],"iteration":933,"passed_time":1.494401917,"remaining_time":0.1056001355},
{"learn":[3.052010876],"iteration":934,"passed_time":1.496023848,"remaining_time":0.1040016579},
{"learn":[3.051901804],"iteration":935,"passed_time":1.497229988,"remaining_time":0.1023747},
{"learn":[3.048060088],"iteration":936,"passed_time":1.498296616,"remaining_time":0.1007392602},
{"learn":[3.046932682],"iteration":937,"passed_time":1.499531186,"remaining_time":0.09911613384},
{"learn":[3.04618418],"iteration":938,"passed_time":1.500584783,"remaining_time":0.09748207855},
{"learn":[3.04211616],"iteration":939,"passed_time":1.501650428,"remaining_time":0.09585002734},
{"learn":[3.04120278],"iteration":940,"passed_time":1.503465379,"remaining_time":0.09426616082},
{"learn":[3.039059688],"iteration":941,"passed_time":1.504545786,"remaining_time":0.09263657705},
{"learn":[3.038679216],"iteration":942,"passed_time":1.505609634,"remaining_time":0.09100715708},
{"learn":[3.036481085],"iteration":943,"passed_time":1.506779907,"remaining_time":0.0893852487},
{"learn":[3.035316244],"iteration":944,"passed_time":1.508312288,"remaining_time":0.08778537128},
{"learn":[3.033227763],"iteration":945,"passed_time":1.510086305,"remaining_time":0.08619942967},
{"learn":[3.032788823],"iteration":946,"passed_time":1.511424116,"remaining_time":0.08458867811},
{"learn":[3.031663233],"iteration":947,"passed_time":1.512631622,"remaining_time":0.08297135482},
{"learn":[3.030620733],"iteration":948,"passed_time":1.513747433,"remaining_time":0.08134996741},
{"learn":[3.029662345],"iteration":949,"passed_time":1.514982615,"remaining_time":0.0797359271},
{"learn":[3.028477011],"iteration":950,"passed_time":1.516961594,"remaining_time":0.07816100747},
{"learn":[3.028216567],"iteration":951,"passed_time":1.51820926,"remaining_time":0.07654836607},
{"learn":[3.02697666],"iteration":952,"passed_time":1.519410113,"remaining_time":0.07493418187},
{"learn":[3.02600432],"iteration":953,"passed_time":1.520579505,"remaining_time":0.07331934722},
{"learn":[3.025275769],"iteration":954,"passed_time":1.521876586,"remaining_time":0.07171146215},
{"learn":[3.022020201],"iteration":955,"passed_time":1.523872662,"remaining_time":0.07013639867},
{"learn":[3.021309205],"iteration":956,"passed_time":1.52524255,"remaining_time":0.06853231937},
{"learn":[3.021192267],"iteration":957,"passed_time":1.526299551,"remaining_time":0.06691501165},
{"learn":[3.018998596],"iteration":958,"passed_time":1.527386546,"remaining_time":0.06530015471},
{"learn":[3.018611196],"iteration":959,"passed_time":1.528948113,"remaining_time":0.06370617137},
{"learn":[3.017668173],"iteration":960,"passed_time":1.530146509,"remaining_time":0.06209751703},
{"learn":[3.016894667],"iteration":961,"passed_time":1.531357964,"remaining_time":0.06049023144},
{"learn":[3.016533995],"iteration":962,"passed_time":1.532416235,"remaining_time":0.05887788236},
{"learn":[3.015295068],"iteration":963,"passed_time":1.533464259,"remaining_time":0.05726630014},
{"learn":[3.014054312],"iteration":964,"passed_time":1.534620442,"remaining_time":0.05565980877},
{"learn":[3.013156416],"iteration":965,"passed_time":1.536106326,"remaining_time":0.05406585414},
{"learn":[3.011929158],"iteration":966,"passed_time":1.53816969,"remaining_time":0.05249183016},
{"learn":[3.010444009],"iteration":967,"passed_time":1.539500798,"remaining_time":0.05089258836},
{"learn":[3.01014292],"iteration":968,"passed_time":1.540515914,"remaining_time":0.04928379084},
{"learn":[3.008807603],"iteration":969,"passed_time":1.54160007,"remaining_time":0.04767835269},
{"learn":[3.00673005],"iteration":970,"passed_time":1.542765376,"remaining_time":0.04607641184},
{"learn":[3.005865406],"iteration":971,"passed_time":1.543918042,"remaining_time":0.04447500531},
{"learn":[3.004845907],"iteration":972,"passed_time":1.544961102,"remaining_time":0.04287147969},
{"learn":[3.003550631],"iteration":973,"passed_time":1.546152993,"remaining_time":0.04127307783},
{"learn":[3.003140545],"iteration":974,"passed_time":1.547223678,"remaining_time":0.03967240199},
{"learn":[3.001748283],"iteration":975,"passed_time":1.548410472,"remaining_time":0.03807566734},
{"learn":[3.001067475],"iteration":976,"passed_time":1.549802891,"remaining_time":0.03648461259},
{"learn":[3.000343489],"iteration":977,"passed_time":1.551545761,"remaining_time":0.03490184738},
{"learn":[2.999483396],"iteration":978,"passed_time":1.553259907,"remaining_time":0.03331813896},
{"learn":[2.998265377],"iteration":979,"passed_time":1.554546105,"remaining_time":0.03172543072},
{"learn":[2.997687191],"iteration":980,"passed_time":1.555787992,"remaining_time":0.03013248914},
{"learn":[2.996882838],"iteration":981,"passed_time":1.557278811,"remaining_time":0.02854482546},
{"learn":[2.994009235],"iteration":982,"passed_time":1.558722301,"remaining_time":0.0269565403},
{"learn":[2.993030785],"iteration":983,"passed_time":1.560047619,"remaining_time":0.02536662795},
{"learn":[2.991087898],"iteration":984,"passed_time":1.561348842,"remaining_time":0.02377688592},
{"learn":[2.990627871],"iteration":985,"passed_time":1.562644557,"remaining_time":0.02218765091},
{"learn":[2.989316662],"iteration":986,"passed_time":1.564348752,"remaining_time":0.02060439086},
{"learn":[2.987805949],"iteration":987,"passed_time":1.566914568,"remaining_time":0.01903135103},
{"learn":[2.986647106],"iteration":988,"passed_time":1.568078316,"remaining_time":0.01744070928},
{"learn":[2.984742337],"iteration":989,"passed_time":1.569417292,"remaining_time":0.01585269991},
{"learn":[2.983143511],"iteration":990,"passed_time":1.570749373,"remaining_time":0.01426513054},
{"learn":[2.981405995],"iteration":991,"passed_time":1.572374242,"remaining_time":0.01268043743},
{"learn":[2.980201676],"iteration":992,"passed_time":1.574019362,"remaining_time":0.01109580618},
{"learn":[2.9792725],"iteration":993,"passed_time":1.575464426,"remaining_time":0.009509845631},
{"learn":[2.975741802],"iteration":994,"passed_time":1.576816854,"remaining_time":0.007923702782},
{"learn":[2.975353198],"iteration":995,"passed_time":1.57956644,"remaining_time":0.006343640322},
{"learn":[2.973988454],"iteration":996,"passed_time":1.58160471,"remaining_time":0.004759091403},
{"learn":[2.972418412],"iteration":997,"passed_time":1.583135815,"remaining_time":0.003172616865},
{"learn":[2.971622036],"iteration":998,"passed_time":1.584465104,"remaining_time":0.001586051155},
{"learn":[2.970552176],"iteration":999,"passed_time":1.585753795,"remaining_time":0}
]}